Workbook

Sheet Part 1
B1: Syntactic Quality | D1: Semantic Quality | F1: Pragmatic Quality
B2: Human | C2: LLM | D2: Human | E2: LLM | F2: Human | G2: LLM
A3: 1 | B3: 0 | C3: 0 | D3: 2 | E3: 9 | F3: 2 | G3: 1
A4: 2 | B4: 3 | C4: 2 | D4: 0 | E4: 3 | F4: 0 | G4: 0
A5: 3 | B5: 0 | C5: 0 | D5: 1 | E5: 14 | F5: 2 | G5: 1
A6: 4 | B6: 0 | C6: 1 | D6: 0 | E6: 5 | F6: 1 | G6: 1
A7: 5 | B7: 1 | C7: 0 | D7: 0 | E7: 6 | F7: 0 | G7: 0 | K7: Syntactic Quality | L7: Semantic Quality | M7: Pragmatic Quality
A8: 6 | B8: 0 | C8: 0 | D8: 7 | E8: 5 | F8: 3 | G8: 3 | J8: Human | K8: =B23 | L8: =D23 | M8: =F23
A9: 7 | B9: 0 | C9: 1 | D9: 0 | E9: 1 | F9: 0 | G9: 2 | J9: LLM | K9: =C23 | L9: =E23 | M9: =G23
A10: 8 | B10: 0 | C10: 1 | D10: 1 | E10: =2 | F10: 1 | G10: 2
A11: 9 | B11: 0 | C11: 1 | D11: 1 | E11: 6 | F11: 4 | G11: 3
A12: 10 | B12: 0 | C12: 2 | D12: 1 | E12: 1 | F12: 1 | G12: 2
A13: 11 | B13: 0 | C13: 1 | D13: 3 | E13: 5 | F13: 2 | G13: 1
A14: 12 | B14: 0 | C14: 1 | D14: 1 | E14: 1 | F14: 0 | G14: 1
A15: 13 | B15: 0 | C15: 0 | D15: 0 | E15: 3 | F15: 1 | G15: 1
A16: 14 | B16: 0 | C16: 0 | D16: 1 | E16: 6 | F16: 1 | G16: 1
A17: 15 | B17: 4 | C17: 1 | D17: 5 | E17: 7 | F17: 0 | G17: 2
A18: 16 | B18: 2 | C18: 2 | D18: 2 | E18: 8 | F18: 2 | G18: 3
A19: 17 | B19: 0 | C19: 0 | D19: 2 | E19: 0 | F19: 1 | G19: 2
A20: 18 | B20: 0 | C20: 2 | D20: 3 | E20: 5 | F20: 1 | G20: 1
A21: 19 | B21: 0 | C21: 1 | D21: 3 | E21: 4 | F21: 0 | G21: 3
A22: 20 | B22: 0 | C22: 2 | D22: 2 | E22: 6 | F22: 0 | G22: 2
A23: Tot | B23: =SUM(B3:B22) | C23: =SUM(C3:C22) | D23: =SUM(D3:D22) | E23: =SUM(E3:E22) | F23: =SUM(F3:F22) | G23: =SUM(G3:G22)

Sheet Part 2 - 1
B2: Given Solution | C2: Human | D2: LLM | E2: Distance Human | F2: Distance LLM
B3: Work Product | C3: Work Product | D3: Work Product | E3: =0 | F3: =0
B4: Work Product .Percent Complete | C4: Work Product .Percent Complete | D4: \ | E4: =SQRT(0^2 + 0^2 + 0^2 + 0^2) | F4: =SQRT(1^2 + 1^2 + 1^2 + 1^2)
B5: Work Product .Description | C5: Work Product .Description | D5: \ | E5: =SQRT(0^2 + 0^2 + 0^2 + 0^2) | F5: =SQRT(1^2 + 1^2 + 1^2 + 1^2)
B6: Work Product .Validate() | C6: Work Product .Validate() | D6: \ | E6: =SQRT(0^2 + 0^2 + 0^2 + 0^2 + 0^2 + 0^2) | F6: =SQRT(1^2 + 1^2 + 1^2 + 1^2 + 0.5^2 + 1^2)
B7: Requirement | C7: Requirement | D7: Requirement | E7: =0 | F7: =0
B8: Requirement .Media | C8: \ | D8: \ | E8: =SQRT(1^2 + 1^2 + 1^2 + 1^2) | F8: =SQRT(1^2 + 1^2 + 1^2 + 1^2)
B9: Requirement .Validate() | C9: \ | D9: Requirement .ValidateWorkProduct() | E9: =SQRT(1^2 + 1^2 + 1^2 + 1^2 + 0.5^2 + 1^2) | F9: =SQRT(0^2 + 0^2 + 0^2 + 1^2 + 0^2 + 0^2)
B10: Requirement .Publish() | C10: Requirement .Publish() | D10: \ | E10: =SQRT(0^2 + 0^2 + 0^2 + 0^2 + 0^2 + 0^2) | F10: =SQRT(1^2 + 1^2 + 1^2 + 1^2 + 0.5^2 + 1^2)
B11: \ | C11: \ | D11: Requirement .percentComplete | E11: =SQRT(0^2 + 0^2 + 0^2 + 0^2 + 0^2 + 0^2) | F11: =SQRT(1^2 + 1^2 + 1^2 + 1^2)
B12: \ | C12: \ | D12: Requirement .Description | E12: =SQRT(0^2 + 0^2 + 0^2 + 0^2 + 0^2 + 0^2) | F12: =SQRT(1^2 + 1^2 + 1^2 + 1^2)
B13: System | C13: System | D13: System | E13: =0 | F13: =0
B14: System .Platform | C14: \ | D14: \ | E14: =SQRT(0^2 + 0^2 + 0^2 + 0^2) | F14: =SQRT(1^2 + 1^2 + 1^2 + 1^2)
B15: System .Validate() | C15: \ | D15: \ | E15: =SQRT(1^2 + 1^2 + 1^2 + 1^2 + 0.5^2 + 1^2) | F15: =SQRT(1^2 + 1^2 + 1^2 + 1^2 + 0.5^2 + 1^2)
B16: System .Deploy() | C16: System .Deploy() | D16: System .Deploy() | E16: =SQRT(0^2 + 0^2 + 0^2 + 0^2 + 0^2 + 0^2) | F16: =SQRT(0^2 + 0^2 + 0^2 + 0^2 + 0^2 + 0^2)
B17: \ | C17: \ | D17: System .PublishRequirements() | E17: =SQRT(0^2 + 0^2 + 0^2 + 0^2 + 0^2 + 0^2) | F17: =SQRT(1^2 + 1^2 + 1^2 + 1^2 + 0.5^2 + 1^2)
B18: Project | C18: Project | D18: Project | E18: =0 | F18: =0
B19: Project .Name | C19: Project .Name | D19: Project .projectID | E19: =SQRT(0^2 + 0^2 + 0^2 + 0^2) | F19: =SQRT(0^2 + 0^2 + 1^2 + 1^2)
B20: Project .Start Date | C20: Project .Start Date | D20: \ | E20: =SQRT(0^2 + 0^2 + 0^2 + 0^2) | F20: =SQRT(1^2 + 1^2 + 1^2 + 1^2)
B21: Project .End Date | C21: Project .End Date | D21: \ | E21: =SQRT(0^2 + 0^2 + 0^2 + 0^2) | F21: =SQRT(1^2 + 1^2 + 1^2 + 1^2)
B22: Manager | C22: Project Manager | D22: Project Manager | E22: =0.5 | F22: =0.5
B23: Manager .Name | C23: Project Manager .Name | D23: Project Manager .Name | E23: =SQRT(0^2 + 0^2 + 0^2 + 0^2) | F23: =SQRT(0^2 + 0^2 + 0^2 + 0^2)
B24: Manager .Phone Number | C24: \ | D24: \ | E24: =SQRT(1^2 + 1^2 + 1^2 + 1^2) | F24: =SQRT(1^2 + 1^2 + 1^2 + 1^2)
B25: Manager .Initiate Project() | C25: ProjectManager .Initiate Project() | D25: ProjectManager .Initiate Project() | E25: =SQRT(0^2 + 0^2 + 0^2 + 0^2 + 0^2 + 0^2) | F25: =SQRT(0^2 + 0^2 + 0^2 + 0^2 + 0^2 + 0^2)
B26: Manager .Terminate Project() | C26: ProjectManager .Terminate Project() | D26: ProjectManager .Terminate Project() | E26: =SQRT(0^2 + 0^2 + 0^2 + 0^2 + 0^2 + 0^2) | F26: =SQRT(0^2 + 0^2 + 0^2 + 0^2 + 0^2 + 0^2)
B27: \ | C27: \ | D27: ProjectManager .startDate | E27: =SQRT(0^2 + 0^2 + 0^2 + 0^2) | F27: =SQRT(1^2 + 1^2 + 1^2 + 1^2)
B28: \ | C28: \ | D28: ProjectManager .endDate | E28: =SQRT(0^2 + 0^2 + 0^2 + 0^2) | F28: =SQRT(1^2 + 1^2 + 1^2 + 1^2)
B29: Team | C29: Team | D29: \ | E29: =0 | F29: =1
B30: Team .Description | C30: Team .Description | D30: \ | E30: =SQRT(0^2 + 0^2 + 0^2 + 0^2) | F30: =SQRT(1^2 + 1^2 + 1^2 + 1^2)
B31: \ | C31: \ | D31: Validation | E31: =SQRT(0^2 + 0^2 + 0^2 + 0^2) | F31: =1
B32: Generalization (Work Product - Requirement) | C32: Generalization (Work Product - Requirement) | D32: Generalization (Work Product - Requirement) | E32: =SQRT(0^2 + 0^2 + 0^2 + 0^2) | F32: =SQRT(1^2 + 1^2 + 0^2 + 0^2)
B33: Generalization (Work Product - System) | C33: Generalization (Work Product - System) | D33: Generalization (Work Product - System) | E33: =SQRT(0^2 + 0^2 + 0^2 + 0^2) | F33: =SQRT(1^2 + 1^2 + 0^2 + 0^2)
B34: Association (Requirement - Project) | C34: Association (Requirement - Project) | D34: Association (Requirement - Project) | E34: =SQRT(0^2 + 0^2 + 0^2 + 0^2) | F34: =SQRT(0^2 + 0^2 + 0^2 + 0^2)
B35: Association (System - Project) | C35: Association (System - Project) | D35: Association (System - Project) | E35: =SQRT(0^2 + 0^2 + 0^2 + 0^2) | F35: =SQRT(0^2 + 0^2 + 0^2 + 0^2)
B36: Association (Project - Manager) | C36: Association (Project - ProjectManager) | D36: Association (Project - ProjectManager) | E36: =SQRT(0^2 + 0^2 + 0^2 + 0^2) | F36: =SQRT(0^2 + 0^2 + 0^2 + 0^2)
B37: Association (Project - Team) | C37: Association (Project - Team) | D37: \ | E37: =SQRT(0^2 + 0^2 + 0^2 + 0^2) | F37: =SQRT(1^2 + 1^2 + 1^2 + 1^2)
B38: Association (Manager - Team) | C38: Association (ProjectManager - Team) | D38: \ | E38: =SQRT(0^2 + 0^2 + 0^2 + 0^2) | F38: =SQRT(1^2 + 1^2 + 1^2 + 1^2)
B39: \ | C39: \ | D39: Association (Work Product - Validation) | E39: =SQRT(0^2 + 0^2 + 0^2 + 0^2) | F39: =SQRT(1^2 + 1^2 + 1^2 + 1^2)
D42: Total Distance | E42: =SQRT(SUMSQ(E3:E39)) | F42: =SQRT(SUMSQ(F3:F39))

Sheet Part 2 - 2
B2: Given Solution | C2: Human | D2: LLM | E2: Distance Human | F2: Distance LLM
B3: Take | C3: Takes | D3: Take | E3: =0.5 | F3: =0
B4: Take .nbr | C4: Takes. natural_numbers | D4: Take .number | E4: =SQRT(0^2 + 0^2 + 0^2 + 0^2) | F4: =SQRT(0^2 + 0^2 + 0^2 + 0^2)
B5: Take .filmed_meters | C5: Takes .filmed_meters | D5: Take .filmLength | E5: =SQRT(0^2 + 0^2 + 0^2 + 0^2) | F5: =SQRT(0^2 + 0^2 + 1^2 + 0^2)
B6: Take .reel | C6: Takes .reel | D6: Take .filmCode | E6: =SQRT(0^2 + 0^2 + 0^2 + 0^2) | F6: =SQRT(0^2 + 0^2 + 1^2 + 0^2)
B7: Setup | C7: Setup | D7: Setup | E7: =0 | F7: =0
B8: Setup .code | C8: Setup .code | D8: Setup .code | E8: =SQRT(0^2 + 0^2 + 0^2 + 0^2) | F8: =SQRT(0^2 + 0^2 + 0^2 + 0^2)
B9: Setup .photographic_pars | C9: Setup .photographic_parameters | D9: Setup .photographicParameters | E9: =SQRT(0^2 + 0^2 + 0^2 + 0^2) | F9: =SQRT(0^2 + 0^2 + 0^2 + 0^2)
B10: \ | C10: \ | D10: Setup .description | E10: =SQRT(0^2 + 0^2 + 0^2 + 0^2) | F10: =SQRT(1^2 + 1^2 + 1^2 + 1^2)
B11: Scene | C11: Scene | D11: Scene | E11: =0 | F11: =0
B12: Scene .code | C12: Scene .code | D12: Scene .code | E12: =SQRT(0^2 + 0^2 + 0^2 + 0^2) | F12: =SQRT(0^2 + 0^2 + 0^2 + 0^2)
B13: Scene .description | C13: Scene .description | D13: Scene .description | E13: =SQRT(0^2 + 0^2 + 0^2 + 0^2) | F13: =SQRT(0^2 + 0^2 + 0^2 + 0^2)
B14: Internal | C14: Internals | D14: Internal | E14: =0.5 | F14: =0
B15: Internal .theater | C15: Internals .teather | D15: \ | E15: =SQRT(0^2 + 0^2 + 0^2 + 0^2) | F15: =SQRT(1^2 + 1^2 + 1^2 + 1^2)
B16: External | C16: Externals | D16: External | E16: =0.5 | F16: =0
B17: External .night_scene | C17: External .night_scene | D17: External .timeofday | E17: =SQRT(0^2 + 0^2 + 0^2 + 0^2) | F17: =SQRT(0^2 + 0^2 + 1^2 + 1^2)
B18: Location | C18: Location | D18: Location | E18: =0 | F18: =0
B19: Location .name | C19: Location .name | D19: Location .code | E19: =SQRT(0^2 + 0^2 + 0^2 + 0^2) | F19: =SQRT(0^2 + 0^2 + 1^2 + 0^2)
B20: Location .address | C20: Location .address | D20: Location .address | E20: =SQRT(0^2 + 0^2 + 0^2 + 0^2) | F20: =SQRT(0^2 + 0^2 + 0^2 + 0^2)
B21: Location .description | C21: Location .description | D21: Location .description | E21: =SQRT(0^2 + 0^2 + 0^2 + 0^2) | F21: =SQRT(0^2 + 0^2 + 0^2 + 0^2)
B22: Association (Take - Setup) | C22: Association (Takes - Setup) | D22: Association (Take - Setup) | E22: =SQRT(0^2 + 0^2 + 0^2 + 0^2) | F22: =SQRT(0^2 + 0^2 + 0^2 + 0^2)
B23: Association (Setup - Scene) | C23: Association (Setup - Scene) | D23: Association (Setup - Scene) | E23: =SQRT(0^2 + 0^2 + 0^2 + 0^2) | F23: =SQRT(0^2 + 0^2 + 0^2 + 0^2)
B24: Generalization (Scene - Internal) | C24: Generalization (Scene - Internals) | D24: Generalization (Scene - Internal) | E24: =SQRT(0^2 + 0^2 + 0^2 + 0^2) | F24: =SQRT(0^2 + 0^2 + 0^2 + 0^2)
B25: Generalization (Scene - Extenal) | C25: Generalization (Scene - Extenals) | D25: Generalization (Scene - Extenal) | E25: =SQRT(0^2 + 0^2 + 0^2 + 0^2) | F25: =SQRT(0^2 + 0^2 + 0^2 + 0^2)
B26: Association (Externals - Location) | C26: Association (External - Location) | D26: Association (External - Location) | E26: =SQRT(0^2 + 0^2 + 0^2 + 0^2) | F26: =SQRT(0^2 + 0^2 + 0^2 + 1^2)
B27: \ | C27: \ | D27: Association (Scene - Internal) | E27: =SQRT(0^2 + 0^2 + 0^2 + 0^2) | F27: =SQRT(1^2 + 1^2 + 1^2 + 1^2)
B28: \ | C28: \ | D28: Association (Scene - External) | E28: =SQRT(0^2 + 0^2 + 0^2 + 0^2) | F28: =SQRT(1^2 + 1^2 + 1^2 + 1^2)
D31: Total Distance | E31: =SQRT(SUMSQ(E3:E28)) | F31: =SQRT(SUMSQ(F3:F28))

Sheet Part 2 - 3
B2: Given Solution | C2: Human | D2: LLM | E2: Distance Human | F2: Distance LLM
B3: Document | C3: Document | D3: Document | E3: =0 | F3: =0
B4: Document .numberofpages | C4: Document .numberofpages | D4: Document .pages | E4: =SQRT(0^2 + 0^2 + 0^2 + 0^2) | F4: =SQRT(0^2 + 0^2 + 0^2 + 1^2)
B5: \ | C5: User | D5: User | E5: =1 | F5: =1
B6: Document .open() | C6: User .open() | D6: User .openDocument() | E6: =SQRT(0^2 + 0^2 + 0^2 + 0^2 + 0^2 + 0^2) | F6: =SQRT(0^2 + 0^2 + 0^2 + 0^2 + 0^2 + 0^2)
B7: Document .save() | C7: User .save() | D7: User .saveDocument() | E7: =SQRT(0^2 + 0^2 + 0^2 + 0^2 + 0^2 + 0^2) | F7: =SQRT(0^2 + 0^2 + 0^2 + 0^2 + 0^2 + 0^2)
B8: Document .print() | C8: User .print() | D8: User .printDocument() | E8: =SQRT(0^2 + 0^2 + 0^2 + 0^2 + 0^2 + 0^2) | F8: =SQRT(0^2 + 0^2 + 0^2 + 0^2 + 0^2 + 0^2)
B9: Document .new() | C9: User .new() | D9: \ | E9: =SQRT(0^2 + 0^2 + 0^2 + 0^2 + 0^2 + 0^2) | F9: =SQRT(1^2 + 1^2 + 1^2 + 1^2 + 0.5^2 + 1^2)
B10: Page | C10: Page | D10: Page | E10: =0 | F10: =0
B11: Page .pageNumber | C11: \ | D11: \ | E11: =SQRT(1^2 + 1^2 + 1^2 + 1^2) | F11: =SQRT(1^2 + 1^2 + 1^2 + 1^2)
B12: Trimming | C12: \ | D12: \ | E12: =0 | F12: =0
B13: Trimming .date | C13: Header/Footer .date | D13: Header/Footer .date | E13: =SQRT(0^2 + 0^2 + 0^2 + 0^2) | F13: =SQRT(0^2 + 0^2 + 0^2 + 0^2)
B14: Trimming .time | C14: Header/Footer .time | D14: Header/Footer .time | E14: =SQRT(0^2 + 0^2 + 0^2 + 0^2) | F14: =SQRT(0^2 + 0^2 + 0^2 + 0^2)
B15: Trimming .pageNumber | C15: Header/Footer .pageNumber | D15: Header/Footer .pageNumber | E15: =SQRT(0^2 + 0^2 + 0^2 + 0^2) | F15: =SQRT(0^2 + 0^2 + 0^2 + 0^2)
B16: \ | C16: Header | D16: Header | E16: =1 | F16: =1
B17: \ | C17: Footer | D17: Footer | E17: =1 | F17: =1
B18: Character | C18: \ | D18: \ | E18: =1 | F18: =1
B19: Character .ASCIICode | C19: \ | D19: \ | E19: =SQRT(1^2 + 1^2 + 1^2 + 1^2) | F19: =SQRT(1^2 + 1^2 + 1^2 + 1^2)
B20: Character .Type | C20: \ | D20: \ | E20: =SQRT(1^2 + 1^2 + 1^2 + 1^2) | F20: =SQRT(1^2 + 1^2 + 1^2 + 1^2)
B21: Table | C21: Table | D21: Table | E21: =0 | F21: =0
B22: Table .rows | C22: Table .rows | D22: Table .rows | E22: =SQRT(0^2 + 0^2 + 0^2 + 0^2) | F22: =SQRT(0^2 + 0^2 + 0^2 + 0^2)
B23: Table .columns | C23: Table .columns | D23: \ | E23: =SQRT(0^2 + 0^2 + 0^2 + 0^2) | F23: =SQRT(1^2 + 1^2 + 1^2 + 1^2)
B24: Picture | C24: Picture | D24: Picture | E24: =0 | F24: =0
B25: Picture .imageType | C25: Picture .imageType | D25: \ | E25: =SQRT(0^2 + 0^2 + 0^2 + 0^2) | F25: =SQRT(1^2 + 1^2 + 1^2 + 1^2)
B26: Picture .imageSize | C26: Picture .imageSize | D26: \ | E26: =SQRT(0^2 + 0^2 + 0^2 + 0^2) | F26: =SQRT(1^2 + 1^2 + 1^2 + 1^2)
B27: Cell | C27: Cell | D27: Cell | E27: =0 | F27: =0
B28: Cell .cellFormat | C28: \ | D28: \ | E28: =SQRT(1^2 + 1^2 + 1^2 + 1^2) | F28: =SQRT(1^2 + 1^2 + 1^2 + 1^2)
B29: \ | C29: Body | D29: Body | E29: =1 | F29: =1
B30: \ | C30: Sentence | D30: Sentence | E30: =1 | F30: =1
B31: \ | C31: Puntuaction | D31: \ | E31: =1 | F31: =0
B32: \ | C32: Word | D32: Word | E32: =1 | F32: =1
B33: \ | C33: \ | D33: ContentItem | E33: =0 | F33: =1
B34: \ | C34: \ | D34: Row | E34: =0 | F34: =1
B35: Composition (Document - Page) | C35: Composition (Document - Page) | D35: Association (Document - Page) | E35: =SQRT(0^2 + 0^2 + 0^2 + 0^2) | F35: =SQRT(0^2 + 0^2 + 1^2 + 1^2)
B36: Aggregation (Page - Trimming) | C36: \ | D36: \ | E36: =SQRT(1^2 + 1^2 + 1^2 + 1^2) | F36: =SQRT(1^2 + 1^2 + 1^2 + 1^2)
B37: Aggregation (Page - Character) | C37: \ | D37: \ | E37: =SQRT(1^2 + 1^2 + 1^2 + 1^2) | F37: =SQRT(1^2 + 1^2 + 1^2 + 1^2)
B38: Aggregation (Page - Table) | C38: \ | D38: \ | E38: =SQRT(1^2 + 1^2 + 1^2 + 1^2) | F38: =SQRT(1^2 + 1^2 + 1^2 + 1^2)
B39: Aggregation (Page - Picture) | C39: \ | D39: \ | E39: =SQRT(1^2 + 1^2 + 1^2 + 1^2) | F39: =SQRT(1^2 + 1^2 + 1^2 + 1^2)
B40: Aggregation (Cell - Character) | C40: \ | D40: \ | E40: =SQRT(1^2 + 1^2 + 1^2 + 1^2) | F40: =SQRT(1^2 + 1^2 + 1^2 + 1^2)
B41: Aggregation (Cell - Picture) | C41: Aggregation (Cell - Picture) | D41: \ | E41: =SQRT(0^2 + 0^2 + 0^2 + 0^2) | F41: =SQRT(1^2 + 1^2 + 1^2 + 1^2)
B42: Composition (Table - Cell) | C42: Composition (Table - Cell) | D42: \ | E42: =SQRT(0^2 + 0^2 + 0^2 + 0^2) | F42: =SQRT(1^2 + 1^2 + 1^2 + 1^2)
B43: \ | C43: Association (User - Document) | D43: Association (User - Document) | E43: =SQRT(1^2 + 1^2 + 1^2 + 1^2) | F43: =SQRT(1^2 + 1^2 + 1^2 + 1^2)
B44: \ | C44: Composition (Header - Page) | D44: Association (Header - Page) | E44: =SQRT(1^2 + 1^2 + 1^2 + 1^2) | F44: =SQRT(1^2 + 1^2 + 1^2 + 1^2)
B45: \ | C45: Composition (Page - Footer) | D45: Association (Page - Footer) | E45: =SQRT(1^2 + 1^2 + 1^2 + 1^2) | F45: =SQRT(1^2 + 1^2 + 1^2 + 1^2)
B46: \ | C46: Composition (Page - Body) | D46: Association (Page - Body) | E46: =SQRT(1^2 + 1^2 + 1^2 + 1^2) | F46: =SQRT(1^2 + 1^2 + 1^2 + 1^2)
B47: \ | C47: Aggregation (Body - Sentence) | D47: \ | E47: =SQRT(1^2 + 1^2 + 1^2 + 1^2) | F47: =SQRT(1^2 + 1^2 + 1^2 + 1^2)
B48: \ | C48: Aggregation (Sentence - Puntuaction) | D48: \ | E48: =SQRT(1^2 + 1^2 + 1^2 + 1^2) | F48: =SQRT(1^2 + 1^2 + 1^2 + 1^2)
B49: \ | C49: Aggregation (Sentence - Word) | D49: \ | E49: =SQRT(1^2 + 1^2 + 1^2 + 1^2) | F49: =SQRT(1^2 + 1^2 + 1^2 + 1^2)
B50: \ | C50: Aggregation (Body - Table) | D50: \ | E50: =SQRT(1^2 + 1^2 + 1^2 + 1^2) | F50: =SQRT(1^2 + 1^2 + 1^2 + 1^2)
B51: \ | C51: Aggregation (Body - Picture) | D51: \ | E51: =SQRT(1^2 + 1^2 + 1^2 + 1^2) | F51: =SQRT(1^2 + 1^2 + 1^2 + 1^2)
B52: \ | C52: \ | D52: Association (Body - ContentItem) | E52: =SQRT(1^2 + 1^2 + 1^2 + 1^2) | F52: =SQRT(1^2 + 1^2 + 1^2 + 1^2)
B53: \ | C53: \ | D53: Generalization (ContentItem - Sentence) | E53: =SQRT(1^2 + 1^2 + 1^2 + 1^2) | F53: =SQRT(1^2 + 1^2 + 1^2 + 1^2)
B54: \ | C54: \ | D54: Generalization (ContentItem - Picture) | E54: =SQRT(1^2 + 1^2 + 1^2 + 1^2) | F54: =SQRT(1^2 + 1^2 + 1^2 + 1^2)
... B57: \ | C57: \ | D57: Association (Row - Cell) | E57: =SQRT(1^2 + 1^2 + 1^2 + 1^2) | F57: =SQRT(1^2 + 1^2 + 1^2 + 1^2)
D60: Total Distance | E60: =SQRT(SUMSQ(E3:E57)) | F60: =SQRT(SUMSQ(F3:F57))

Sheet Part 2 - 4
B2: Given Solution | C2: Human | D2: LLM | E2: Distance Human | F2: Distance LLM
B3: FamilyInsured | C3: Family | D3: Family | E3: =0 | F3: =0
B4: FamilyInsured .NameofFamilyHead | C4: Family .NameofFamilyHead | D4: Family .HeadofFamily | E4: =SQRT(0^2 + 0^2 + 0^2 + 0^2) | F4: =SQRT(0^2 + 0^2 + 0^2 + 0^2)
B5: FamilyInsured .Address | C5: Family .address | D5: \ | E5: =SQRT(0^2 + 0^2 + 0^2 + 0^2) | F5: =SQRT(1^2 + 1^2 + 1^2 + 1^2)
B6: FamilyInsured .Telephone | C6: Family .telephone | D6: \ | E6: =SQRT(0^2 + 0^2 + 0^2 + 0^2) | F6: =SQRT(1^2 + 1^2 + 1^2 + 1^2)
B7: FamilyInsured .InsuranceCarrier | C7: Family .Insurancecarrier | D7: \ | E7: =SQRT(0^2 + 0^2 + 0^2 + 0^2) | F7: =SQRT(1^2 + 1^2 + 1^2 + 1^2)
B8: FamilyInsured .PolicyNumber | C8: Family .PolicyNumber | D8: \ | E8: =SQRT(0^2 + 0^2 + 0^2 + 0^2) | F8: =SQRT(1^2 + 1^2 + 1^2 + 1^2)
B9: Doctor | C9: Doctor | D9: Doctor | E9: =0 | F9: =0
B10: Doctor .Name | C10: Doctor .Name | D10: \ | E10: =SQRT(0^2 + 0^2 + 0^2 + 0^2) | F10: =SQRT(1^2 + 1^2 + 1^2 + 1^2)
B11: Doctor .Specialty | C11: Doctor .Specialty | D11: \ | E11: =SQRT(0^2 + 0^2 + 0^2 + 0^2) | F11: =SQRT(1^2 + 1^2 + 1^2 + 1^2)
B12: Doctor .Address | C12: Doctor .Address | D12: \ | E12: =SQRT(0^2 + 0^2 + 0^2 + 0^2) | F12: =SQRT(1^2 + 1^2 + 1^2 + 1^2)
B13: Doctor .Telephone | C13: Doctor .Telephone | D13: \ | E13: =SQRT(0^2 + 0^2 + 0^2 + 0^2) | F13: =SQRT(1^2 + 1^2 + 1^2 + 1^2)
B14: Doctor .PagerNumber | C14: \ | D14: \ | E14: =SQRT(1^2 + 1^2 + 1^2 + 1^2) | F14: =SQRT(1^2 + 1^2 + 1^2 + 1^2)
B15: Doctor .SSN | C15: \ | D15: \ | E15: =SQRT(1^2 + 1^2 + 1^2 + 1^2) | F15: =SQRT(1^2 + 1^2 + 1^2 + 1^2)
B16: Patient | C16: Patient | D16: Patient | E16: =0 | F16: =0
B17: Patient .Name | C17: Patient .Name | D17: \ | E17: =SQRT(0^2 + 0^2 + 0^2 + 0^2) | F17: =SQRT(1^2 + 1^2 + 1^2 + 1^2)
B18: Patient .Gender | C18: Patient .Gender | D18: \ | E18: =SQRT(0^2 + 0^2 + 0^2 + 0^2) | F18: =SQRT(1^2 + 1^2 + 1^2 + 1^2)
B19: Patient .Birthdate | C19: Patient .Birthdate | D19: \ | E19: =SQRT(0^2 + 0^2 + 0^2 + 0^2) | F19: =SQRT(1^2 + 1^2 + 1^2 + 1^2)
B20: Patient .LastVisitDate | C20: Patient .LastVisitDate | D20: \ | E20: =SQRT(0^2 + 0^2 + 0^2 + 0^2) | F20: =SQRT(1^2 + 1^2 + 1^2 + 1^2)
B21: Patient .Allergies | C21: Patient .Allergies | D21: \ | E21: =SQRT(0^2 + 0^2 + 0^2 + 0^2) | F21: =SQRT(1^2 + 1^2 + 1^2 + 1^2)
B22: Patient .Notes | C22: Patient .Notes | D22: \ | E22: =SQRT(0^2 + 0^2 + 0^2 + 0^2) | F22: =SQRT(1^2 + 1^2 + 1^2 + 1^2)
B23: Visit | C23: Visit | D23: Visit | E23: =0 | F23: =0
B24: Visit .Date | C24: Visit .Date | D24: Visit .Date | E24: =SQRT(0^2 + 0^2 + 0^2 + 0^2) | F24: =SQRT(0^2 + 0^2 + 0^2 + 0^2)
B25: Visit .Weight | C25: \ | D25: \ | E25: =SQRT(1^2 + 1^2 + 1^2 + 1^2) | F25: =SQRT(1^2 + 1^2 + 1^2 + 1^2)
B26: Visit .BloodPressure | C26: \ | D26: \ | E26: =SQRT(1^2 + 1^2 + 1^2 + 1^2) | F26: =SQRT(1^2 + 1^2 + 1^2 + 1^2)
B27: Visit .Temperature | C27: \ | D27: \ | E27: =SQRT(1^2 + 1^2 + 1^2 + 1^2) | F27: =SQRT(1^2 + 1^2 + 1^2 + 1^2)
B28: Visit .Reason | C28: Visit .Reason | D28: \ | E28: =SQRT(0^2 + 0^2 + 0^2 + 0^2) | F28: =SQRT(1^2 + 1^2 + 1^2 + 1^2)
B29: Visit .DiagnosisNotes | C29: Visit .DiagnosisNotes | D29: Visit .diagnosis | E29: =SQRT(0^2 + 0^2 + 0^2 + 0^2) | F29: =SQRT(0^2 + 0^2 + 0^2 + 0^2)
B30: Visit .TreatmentNotes | C30: Visit .TreatmentNotes | D30: Visit .medications | E30: =SQRT(0^2 + 0^2 + 0^2 + 0^2) | F30: =SQRT(0^2 + 0^2 + 0^2 + 0^2)
B31: \ | C31: Receptionist | D31: Receptionist | E31: =1 | F31: =1
B32: \ | C32: Nurse | D32: Nurse | E32: =1 | F32: =1
B33: \ | C33: \ | D33: User | E33: =0 | F33: =1
B34: \ | C34: \ | D34: Person | E34: =0 | F34: =1
B35: Appointment | C35: Appointment | D35: Appointment | E35: =0 | F35: =0
B36: Appointment .Date | C36: Appointment .Date | D36: Appointment .Date | E36: =SQRT(0^2 + 0^2 + 0^2 + 0^2) | F36: =SQRT(0^2 + 0^2 + 0^2 + 0^2)
B37: Appointment .Time | C37: Appointment .Time | D37: Appointment .Time | E37: =SQRT(0^2 + 0^2 + 0^2 + 0^2) | F37: =SQRT(0^2 + 0^2 + 0^2 + 0^2)
B38: Appointment .Reason | C38: Appointment .Reason | D38: \ | E38: =SQRT(0^2 + 0^2 + 0^2 + 0^2) | F38: =SQRT(1^2 + 1^2 + 1^2 + 1^2)
B39: Prescription | C39: Prescription | D39: Medication | E39: =0 | F39: =0.5
B40: Prescription .Date | C40: Prescription .Date | D40: \ | E40: =SQRT(0^2 + 0^2 + 0^2 + 0^2) | F40: =SQRT(1^2 + 1^2 + 1^2 + 1^2)
B41: Prescription .Medication | C41: Prescription .Medication | D41: Medication .name | E41: =SQRT(0^2 + 0^2 + 0^2 + 0^2) | F41: =SQRT(0^2 + 0^2 + 1^2 + 0^2)
B42: Prescription .Dosage | C42: Prescription .Dosage | D42: Medication .dose | E42: =SQRT(0^2 + 0^2 + 0^2 + 0^2) | F42: =SQRT(0^2 + 0^2 + 0^2 + 0^2)
B43: Prescription .Number | C43: \ | D43: \ | E43: =SQRT(1^2 + 1^2 + 1^2 + 1^2) | F43: =SQRT(1^2 + 1^2 + 1^2 + 1^2)
B44: Association (FamilyInsured - Patient) | C44: Association (Family - Patient) | D44: Composition (Family - Patient) | E44: =SQRT(0^2 + 0^2 + 0^2 + 0^2) | F44: =SQRT(0^2 + 0^2 + 1^2 + 1^2)
B45: Association (FamilyInsured - Doctor) | C45: Association (Family - Doctor) | D45: \ | E45: =SQRT(0^2 + 0^2 + 0^2 + 0^2) | F45: =SQRT(1^2 + 1^2 + 1^2 + 1^2)
B46: Association (Doctor - Visit) | C46: Association (Doctor - Visit) | D46: \ | E46: =SQRT(0^2 + 0^2 + 0^2 + 0^2) | F46: =SQRT(1^2 + 1^2 + 1^2 + 1^2)
B47: Association (Patient - Visit) | C47: Association (Patient - Visit) | D47: Composition (Patient - Visit) | E47: =SQRT(0^2 + 0^2 + 0^2 + 0^2) | F47: =SQRT(0^2 + 0^2 + 1^2 + 0^2)
B48: Association (Patient - Appointment) | C48: Association (Patient - Appointment) | D48: Composition (Patient - Appointment) | E48: =SQRT(0^2 + 0^2 + 0^2 + 0^2) | F48: =SQRT(0^2 + 0^2 + 1^2 + 0^2)
B49: Association (Visit - Appointment) | C49: Association (Visit - Appointment) | D49: \ | E49: =SQRT(0^2 + 0^2 + 0^2 + 0^2) | F49: =SQRT(1^2 + 1^2 + 1^2 + 1^2)
B50: Association (Visit - Prescription) | C50: Association (Visit - Prescription) | D50: Composition (Visit - Medication) | E50: =SQRT(0^2 + 0^2 + 0^2 + 0^2) | F50: =SQRT(0^2 + 0^2 + 1^2 + 0^2)
B51: \ | C51: Association (Patient - Receptionist) | D51: \ | E51: =SQRT(1^2 + 1^2 + 1^2 + 1^2) | F51: =SQRT(0^2 + 0^2 + 0^2 + 0^2)
B52: \ | C52: Association (Receptionist - Appointment) | D52: \ | E52: =SQRT(1^2 + 1^2 + 1^2 + 1^2) | F52: =SQRT(0^2 + 0^2 + 0^2 + 0^2)
B53: \ | C53: Association (Nurse - Visit) | D53: \ | E53: =SQRT(1^2 + 1^2 + 1^2 + 1^2) | F53: =SQRT(0^2 + 0^2 + 0^2 + 0^2)
B54: \ | C54: \ | D54: Generalization (Person - Patient) | E54: =SQRT(0^2 + 0^2 + 0^2 + 0^2) | F54: =SQRT(1^2 + 1^2 + 1^2 + 1^2)
B55: \ | C55: \ | D55: Generalization (User - Receptionist) | E55: =SQRT(0^2 + 0^2 + 0^2 + 0^2) | F55: =SQRT(1^2 + 1^2 + 1^2 + 1^2)
B56: \ | C56: \ | D56: Generalization (User - Nurse) | E56: =SQRT(0^2 + 0^2 + 0^2 + 0^2) | F56: =SQRT(1^2 + 1^2 + 1^2 + 1^2)
B57: \ | C57: \ | D57: Generalization (User - Doctor) | E57: =SQRT(0^2 + 0^2 + 0^2 + 0^2) | F57: =SQRT(1^2 + 1^2 + 1^2 + 1^2)
D60: Total Distance | E60: =SQRT(SUMSQ(E3:E57)) | F60: =SQRT(SUMSQ(F3:F57))

Sheet Part 2 - 5
B2: Given Solution | C2: Human | D2: LLM | E2: Distance Human | F2: Distance LLM
B3: User | C3: User | D3: User | E3: =0 | F3: =0
B4: User .name | C4: User .firstname | D4: User .name | E4: =SQRT(0^2 + 0^2 + 0^2 + 0^2) | F4: =SQRT(0^2 + 0^2 + 0^2 + 0^2)
B5: User .surname | C5: User .lastname | D5: \ | E5: =SQRT(0^2 + 0^2 + 0^2 + 0^2) | F5: =SQRT(1^2 + 1^2 + 1^2 + 1^2)
B6: Subscriber | C6: Subscriber | D6: Subscriber | E6: =0 | F6: =0
B7: Subscriber .phone | C7: Subscriber .telephone | D7: \ | E7: =SQRT(0^2 + 0^2 + 0^2 + 0^2) | F7: =SQRT(1^2 + 1^2 + 1^2 + 1^2)
B8: Subscriber .address | C8: Subscriber .address | D8: \ | E8: =SQRT(0^2 + 0^2 + 0^2 + 0^2) | F8: =SQRT(1^2 + 1^2 + 1^2 + 1^2)
B9: \ | C9: \ | D9: Subscriber .hireMovie() | E9: \ | F9: =SQRT(1^2 + 1^2 + 1^2 + 1^2 + 0.5^2 + 1^2)
B10: \ | C10: \ | D10: Subscriber .buyMovie() | E10: \ | F10: =SQRT(1^2 + 1^2 + 1^2 + 1^2 + 0.5^2 + 1^2)
B11: Card | C11: Card | D11: Recheargeable Card | E11: =0 | F11: =0
B12: Card .credit | C12: Card .credit | D12: Recheargeable Card .credit | E12: =SQRT(0^2 + 0^2 + 0^2 + 0^2) | F12: =SQRT(0^2 + 0^2 + 0^2 + 0^2)
B13: Card .code | C13: Card .code | D13: Recheargeable Card .cardNumber | E13: =SQRT(0^2 + 0^2 + 0^2 + 0^2) | F13: =SQRT(0^2 + 0^2 + 1^2 + 0^2)
B14: Movie-Shop | C14: Movie-Shop | D14: MovieShopSystem | E14: =0 | F14: =0
B15: Movie-Shop .listmovies() | C15: Movie-Shop .listmovies() | D15: Movie-Shop .browseCatalogue() | E15: =SQRT(0^2 + 0^2 + 0^2 + 0^2 + 0^2 + 0^2) | F15: =SQRT(0^2 + 0^2 + 0^2 + 1^2 + 0^2 + 0^2)
B16: Movie-Shop .order() | C16: Movie-Shop .order() | D16: MovieShopSystem .orderMovie() | E16: =SQRT(0^2 + 0^2 + 0^2 + 0^2 + 0^2 + 0^2) | F16: =SQRT(0^2 + 0^2 + 0^2 + 0^2 + 0^2 + 0^2)
B17: Movie-Shop .subscribe() | C17: Movie-Shop .subscribe() | D17: MovieShopSystem .handleSubscription() | E17: =SQRT(0^2 + 0^2 + 0^2 + 0^2 + 0^2 + 0^2) | F17: =SQRT(0^2 + 0^2 + 0^2 + 0^2 + 0^2 + 0^2)
B18: Order | C18: Order | D18: Order | E18: =0 | F18: =0
B19: Order .date | C19: Order .date | D19: Order .orderDate | E19: =SQRT(0^2 + 0^2 + 0^2 + 0^2) | F19: =SQRT(0^2 + 0^2 + 0^2 + 0^2)
B20: Order .user | C20: Order .user | D20: Order .User | E20: =SQRT(0^2 + 0^2 + 0^2 + 0^2) | F20: =SQRT(0^2 + 0^2 + 0^2 + 0^2)
B21: Movie | C21: Movie | D21: Movie | E21: =0 | F21: =0
B22: Movie .name | C22: Movie .name | D22: Movie .title | E22: =SQRT(0^2 + 0^2 + 0^2 + 0^2) | F22: =SQRT(0^2 + 0^2 + 1^2 + 0^2)
B23: \ | C23: \ | D23: Movie .available | E23: =SQRT(0^2 + 0^2 + 0^2 + 0^2) | F23: =SQRT(1^2 + 1^2 + 1^2 + 1^2)
B24: Movie .type | C24: \ | D24: \ | E24: =SQRT(1^2 + 1^2 + 1^2 + 1^2) | F24: =SQRT(1^2 + 1^2 + 1^2 + 1^2)
B25: Movie-Buy | C25: Movie-Buy | D25: \ | E25: =0 | F25: =SQRT(1^2 + 1^2 + 1^2 + 1^2)
B26: Movie-Buy .status | C26: Movie-Buy .state | D26: \ | E26: =SQRT(0^2 + 0^2 + 0^2 + 0^2) | F26: =SQRT(1^2 + 1^2 + 1^2 + 1^2)
B27: Movie-Buy .Price-Sell | C27: Movie-Buy .sellingprice | D27: \ | E27: =SQRT(0^2 + 0^2 + 0^2 + 0^2) | F27: =SQRT(1^2 + 1^2 + 1^2 + 1^2)
B28: Movie-Rent | C28: Movie-Rent | D28: \ | E28: =0 | F28: =SQRT(1^2 + 1^2 + 1^2 + 1^2)
B29: Movie-Rent .status | C29: Movie-Rent .state | D29: \ | E29: =SQRT(0^2 + 0^2 + 0^2 + 0^2) | F29: =SQRT(1^2 + 1^2 + 1^2 + 1^2)
B30: Movie-Rent .date | C30: Movie-Rent .date | D30: \ | E30: =SQRT(0^2 + 0^2 + 0^2 + 0^2) | F30: =SQRT(1^2 + 1^2 + 1^2 + 1^2)
B31: Movie-Rent .Price | C31: Movie-Rent .rentingprice | D31: \ | E31: =SQRT(0^2 + 0^2 + 0^2 + 0^2) | F31: =SQRT(1^2 + 1^2 + 1^2 + 1^2)
B32: Generalization (User - Subscriber) | C32: Generalization (User - Subscriber) | D32: Generalization (User - Subscriber) | E32: =SQRT(0^2 + 0^2 + 0^2 + 0^2) | F32: =SQRT(0^2 + 0^2 + 0^2 + 0^2)
B33: Association (User - Movie-Shop) | C33: Association (User - Movie-Shop) | D33: \ | E33: =SQRT(0^2 + 0^2 + 0^2 + 0^2) | F33: =SQRT(1^2 + 1^2 + 1^2 + 1^2)
B34: Association (Movie-Shop - Card) | C34: Association (Movie-Shop - Card) | D34: \ | E34: =SQRT(0^2 + 0^2 + 0^2 + 0^2) | F34: =SQRT(1^2 + 1^2 + 1^2 + 1^2)
B35: Association (Subscriber - Card) | C35: Association (Subscriber - Card) | D35: Association (Subscriber - RecheargableCard) | E35: =SQRT(0^2 + 0^2 + 0^2 + 0^2) | F35: =SQRT(0^2 + 0^2 + 0^2 + 0^2)
B36: Aggregation (Movie-Shop - Movie) | C36: Aggregation (Movie-Shop - Movie) | D36: Association (MovieShopSystem - Movie) | E36: =SQRT(0^2 + 0^2 + 0^2 + 0^2) | F36: =SQRT(0^2 + 0^2 + 1^2 + 0^2)
B37: Association (Movie-Shop - Order) | C37: Association (Movie-Shop - Order) | D37: Association (MovieShopSystem - Order) | E37: =SQRT(0^2 + 0^2 + 0^2 + 0^2) | F37: =SQRT(0^2 + 0^2 + 0^2 + 0^2)
B38: Association (Order - Movie-Buy) | C38: Association (Order - Movie-Buy) | D38: \ | E38: =SQRT(0^2 + 0^2 + 0^2 + 0^2) | F38: =SQRT(1^2 + 1^2 + 1^2 + 1^2)
B39: Association (User - Movie-Buy) | C39: Association (User - Movie-Buy) | D39: \ | E39: =SQRT(0^2 + 0^2 + 0^2 + 0^2) | F39: =SQRT(1^2 + 1^2 + 1^2 + 1^2)
B40: Association (Subscriber - Movie-Rent) | C40: Association (Subscriber - Movie-Rent) | D40: \ | E40: =SQRT(0^2 + 0^2 + 0^2 + 0^2) | F40: =SQRT(1^2 + 1^2 + 1^2 + 1^2)
B41: Generalization (Movie - Movie-Rent) | C41: Generalization (Movie - Movie-Rent) | D41: \ | E41: =SQRT(0^2 + 0^2 + 0^2 + 0^2) | F41: =SQRT(1^2 + 1^2 + 1^2 + 1^2)
B42: Generalization (Movie - Movie-Buy) | C42: Generalization (Movie - Movie-Buy) | D42: \ | E42: =SQRT(0^2 + 0^2 + 0^2 + 0^2) | F42: =SQRT(1^2 + 1^2 + 1^2 + 1^2)
B43: \ | C43: \ | D43: Association (MovieShopSystem - Subscriber) | E43: =SQRT(0^2 + 0^2 + 0^2 + 0^2) | F43: =SQRT(1^2 + 1^2 + 1^2 + 1^2)
B44: \ | C44: \ | D44: Association (Order - Movie) | E44: =SQRT(0^2 + 0^2 + 0^2 + 0^2) | F44: =SQRT(1^2 + 1^2 + 1^2 + 1^2)
B45: \ | C45: \ | D45: Association (Order - User) | E45: =SQRT(0^2 + 0^2 + 0^2 + 0^2) | F45: =SQRT(1^2 + 1^2 + 1^2 + 1^2)
D48: Total Distance | E48: =SQRT(SUMSQ(E3:E45)) | F48: =SQRT(SUMSQ(F3:F45))

Sheet Part 2 - 6
B2: Given Solution | C2: Human | D2: LLM | E2: Distance Human | F2: Distance LLM
B3: Airline | C3: Airline | D3: Airline | E3: =0 | F3: =0
B4: Airline .ID | C4: Airline .ID | D4: Airline .ID | E4: =SQRT(0^2 + 0^2 + 0^2 + 0^2) | F4: =SQRT(0^2 + 0^2 + 0^2 + 0^2)
B5: Airline .Name | C5: \ | D5: \ | E5: =SQRT(1^2 + 1^2 + 1^2 + 1^2) | F5: =SQRT(1^2 + 1^2 + 1^2 + 1^2)
B6: Aircraft | C6: Aircraft | D6: Aircraft | E6: =0 | F6: =0
B7: Aircraft .Name | C7: Aircraft .Id | D7: \ | E7: =SQRT(0^2 + 0^2 + 1^2 + 0^2) | F7: =SQRT(1^2 + 1^2 + 1^2 + 1^2)
B8: Aircraft .repair | C8: Aircraft .WorkingState | D8: Aircraft .WorkingState | E8: =SQRT(0^2 + 0^2 + 1^2 + 0^2) | F8: =SQRT(0^2 + 0^2 + 1^2 + 0^2)
B9: Aircraft .landed | C9: Aircraft .landed | D9: Aircraft .status | E9: =SQRT(0^2 + 0^2 + 0^2 + 0^2) | F9: =SQRT(0^2 + 0^2 + 1^2 + 0^2)
B10: \ | C10: \ | D10: Aircraft .type | E10: =SQRT(0^2 + 0^2 + 0^2 + 0^2) | F10: =SQRT(1^2 + 1^2 + 1^2 + 1^2)
B11: Flight | C11: Flight | D11: Flight | E11: =0 | F11: =0
B12: Flight .ID | C12: Flight .ID | D12: Flight .ID | E12: =SQRT(0^2 + 0^2 + 0^2 + 0^2) | F12: =SQRT(0^2 + 0^2 + 0^2 + 0^2)
B13: Flight .arrival_time | C13: Flight .arrival_time | D13: Flight .arrival_time | E13: =SQRT(0^2 + 0^2 + 0^2 + 0^2) | F13: =SQRT(0^2 + 0^2 + 0^2 + 0^2)
B14: Flight .departure_time | C14: Flight .departure_time | D14: Flight .departure_time | E14: =SQRT(0^2 + 0^2 + 0^2 + 0^2) | F14: =SQRT(0^2 + 0^2 + 0^2 + 0^2)
B15: Airport | C15: Airport | D15: Airport | E15: =0 | F15: =0
B16: Airport .ID | C16: Airport .Identifier | D16: Airport .code | E16: =SQRT(0^2 + 0^2 + 0^2 + 0^2) | F16: =SQRT(0^2 + 0^2 + 1^2 + 0^2)
B17: Airport .name | C17: \ | D17: Airport .name | E17: =SQRT(1^2 + 1^2 + 1^2 + 1^2) | F17: =SQRT(0^2 + 0^2 + 0^2 + 0^2)
B18: AircraftType | C18: TypeofAircraft | D18: \ | E18: =0 | F18: =1
B19: AircraftType .name | C19: TypeofAircraft .name | D19: \ | E19: =SQRT(0^2 + 0^2 + 0^2 + 0^2) | F19: =SQRT(1^2 + 1^2 + 1^2 + 1^2)
B20: Pilot | C20: Pilot | D20: Pilot | E20: =0 | F20: =0
B21: Pilot .name | C21: Pilot .name | D21: \ | E21: =SQRT(0^2 + 0^2 + 0^2 + 0^2) | F21: =SQRT(1^2 + 1^2 + 1^2 + 1^2)
B22: Pilot 1 | C22: \ | D22: \ | E22: =1 | F22: =1
B23: Pilot 2 | C23: \ | D23: \ | E23: =1 | F23: =1
B24: Pilot 3 | C24: \ | D24: \ | E24: =1 | F24: =1
B25: \ | C25: \ | D25: Company | E25: =0 | F25: =1
B26: Association (Airline - Flight) | C26: Association (Airline - Flight) | D26: Association (Airline - Flight) | E26: =SQRT(0^2 + 0^2 + 0^2 + 1^2) | F26: =SQRT(0^2 + 0^2 + 0^2 + 0^2)
B27: Association (Flight - Airport) | C27: Association (Flight - Airport) | D27: Association (Flight - Airport) | E27: =SQRT(0^2 + 0^2 + 0^2 + 1^2) | F27: =SQRT(0^2 + 0^2 + 0^2 + 0^2)
B28: Association (Airport - Flight) | C28: \ | D28: Association (Airport - Flight) | E28: =SQRT(1^2 + 1^2 + 1^2 + 1^2) | F28: =SQRT(0^2 + 0^2 + 0^2 + 0^2)
B29: Association (Airline - Aircraft) | C29: Association (Airline - Aircraft) | D29: Association (Airline - Aircraft) | E29: =SQRT(0^2 + 0^2 + 0^2 + 1^2) | F29: =SQRT(0^2 + 0^2 + 0^2 + 1^2)
B30: Association (Flight - Aircraft) | C30: Association (Flight - Aircraft) | D30: \ | E30: =SQRT(0^2 + 0^2 + 0^2 + 1^2) | F30: =SQRT(1^2 + 1^2 + 1^2 + 1^2)
B31: Association (Flight - Pilot) | C31: Association (Flight - Pilot) | D31: Association (Flight - Pilot) | E31: =SQRT(0^2 + 0^2 + 0^2 + 0^2) | F31: =SQRT(0^2 + 0^2 + 0^2 + 1^2)
B32: \ | C32: \ | D32: Association (Pilot - Flight) | E32: =SQRT(0^2 + 0^2 + 0^2 + 0^2) | F32: =SQRT(1^2 + 1^2 + 1^2 + 1^2)
B33: Association (Aircraft - Aircraft Type) | C33: Association (Aircraft - TypeofAircraft) | D33: \ | E33: =SQRT(0^2 + 0^2 + 0^2 + 1^2) | F33: =SQRT(1^2 + 1^2 + 1^2 + 1^2)
B34: Association (Aircraft Type - Pilot 3) | C34: \ | D34: \ | E34: =SQRT(1^2 + 1^2 + 1^2 + 1^2) | F34: =SQRT(1^2 + 1^2 + 1^2 + 1^2)
B35: Association (Aircraft Type - Pilot) | C35: Association (TypeofAircraft - Pilot) | D35: \ | E35: =SQRT(0^2 + 0^2 + 0^2 + 1^2) | F35: =SQRT(1^2 + 1^2 + 1^2 + 1^2)
B36: Association (Pilot - Aircraft Type) | C36: \ | D36: \ | E36: =SQRT(1^2 + 1^2 + 1^2 + 1^2) | F36: =SQRT(1^2 + 1^2 + 1^2 + 1^2)
B37: Generalization (Pilot - Pilot1) | C37: \ | D37: \ | E37: =SQRT(1^2 + 1^2 + 1^2 + 1^2) | F37: =SQRT(1^2 + 1^2 + 1^2 + 1^2)
B38: Generalization (Pilot - Pilot2) | C38: \ | D38: \ | E38: =SQRT(1^2 + 1^2 + 1^2 + 1^2) | F38: =SQRT(1^2 + 1^2 + 1^2 + 1^2)
B39: Generalization (Pilot - Pilot3) | C39: \ | D39: \ | E39: =SQRT(1^2 + 1^2 + 1^2 + 1^2) | F39: =SQRT(1^2 + 1^2 + 1^2 + 1^2)
B40: \ | C40: \ | D40: Asssociation (Pilot - Company) | E40: =SQRT(0^2 + 0^2 + 0^2 + 0^2) | F40: =SQRT(1^2 + 1^2 + 1^2 + 1^2)
D43: Total Distance | E43: =SQRT(SUMSQ(E3:E40)) | F43: =SQRT(SUMSQ(F3:F40))

Sheet Part 2 - 7
B2: Given Solution | C2: Human | D2: LLM | E2: Distance Human | F2: Distance LLM
B3: Customer | C3: Customer | D3: Customer | E3: =0 | F3: =0
B4: Customer .Name | C4: Customer .Name | D4: Customer .Name | E4: =SQRT(0^2 + 0^2 + 0^2 + 0^2) | F4: =SQRT(0^2 + 0^2 + 0^2 + 0^2)
B5: Customer .Address | C5: Customer .Address | D5: Customer .Address | E5: =SQRT(0^2 + 0^2 + 0^2 + 0^2) | F5: =SQRT(0^2 + 0^2 + 0^2 + 0^2)
B6: Account | C6: Account | D6: Account | E6: =0 | F6: =0
B7: Account .CashBalance | C7: Account .Balance | D7: Account .Balance | E7: =SQRT(0^2 + 0^2 + 0^2 + 0^2) | F7: =SQRT(0^2 + 0^2 + 0^2 + 0^2)
B8: InvestmentAccount | C8: Investments | D8: InvestmentAccount | E8: =0 | F8: =0
B9: SavingAccount | C9: Savings | D9: SavingsAccount | E9: =0 | F9: =0
B10: SavingAccount .interestRate | C10: Savings .interestrate | D10: SavingsAccount .interestRate | E10: =SQRT(0^2 + 0^2 + 0^2 + 0^2) | F10: =SQRT(0^2 + 0^2 + 0^2 + 0^2)
B11: Stock | C11: Stock | D11: \ | E11: =0 | F11: =1
B12: Stock .ticker | C12: \ | D12: StockOrder .Ticker | E12: =SQRT(1^2 + 1^2 + 1^2 + 1^2) | F12: =SQRT(1^2 + 0^2 + 0^2 + 0^2)
B13: Stock .quantity | C13: Stock .quantity | D13: StockOrder .Quantity | E13: =SQRT(0^2 + 0^2 + 0^2 + 0^2) | F13: =SQRT(1^2 + 0^2 + 0^2 + 0^2)
B14: \ | C14: Stock .price | D14: \ | E14: =SQRT(1^2 + 1^2 + 1^2 + 1^2) | F14: =SQRT(0^2 + 0^2 + 0^2 + 0^2)
B15: StockOrder | C15: StockOrder | D15: StockOrder | E15: =0 | F15: =0
B16: StockOrder .commission | C16: StockOrder .commission | D16: StockOrder .commission | E16: =SQRT(0^2 + 0^2 + 0^2 + 0^2) | F16: =SQRT(0^2 + 0^2 + 0^2 + 0^2)
B17: Association (Customer - Account) | C17: Association (Customer - Account) | D17: Association (Customer - Account) | E17: =SQRT(0^2 + 0^2 + 0^2 + 0^2) | F17: =SQRT(0^2 + 0^2 + 0^2 + 0^2)
B18: Generalization (Account - InvestmentAccount) | C18: Generalization (Account - Investments) | D18: Generalization (Account - InvestmentAccount) | E18: =SQRT(0^2 + 0^2 + 0^2 + 0^2) | F18: =SQRT(0^2 + 0^2 + 0^2 + 0^2)
B19: Generalization (Account - SavingAccount) | C19: Generalization (Account - Savings) | D19: Generalization (Account - SavingAccount) | E19: =SQRT(0^2 + 0^2 + 0^2 + 0^2) | F19: =SQRT(0^2 + 0^2 + 0^2 + 0^2)
B20: Association (InvestmentAccount - Stock) | C20: Association (Investments - Stock) | D20: Association (InvestmentAccount - StockOrder) | E20: =SQRT(0^2 + 0^2 + 0^2 + 0^2) | F20: =SQRT(0^2 + 1^2 + 0^2 + 0^2)
B21: Association (Stock - StockOrder) | C21: Association (Stock - StockOrder) | D21: \ | E21: =SQRT(0^2 + 0^2 + 0^2 + 0^2) | F21: =SQRT(1^2 + 1^2 + 1^2 + 1^2)
D24: Total Distance | E24: =SQRT(SUMSQ(E3:E21)) | F24: =SQRT(SUMSQ(F3:F21))

Sheet Part 2 - 8
B2: Given Solution | C2: Human | D2: LLM | E2: Distance Human | F2: Distance LLM
B3: Animal | C3: Animal | D3: Animal | E3: =0 | F3: =0
B4: Animal . ID | C4: Animal . ID | D4: Animal . ID | E4: =SQRT(0^2 + 0^2 + 0^2 + 0^2) | F4: =SQRT(0^2 + 0^2 + 0^2 + 0^2)
B5: Animal .Name | C5: Animal .Name | D5: Animal .Name | E5: =SQRT(0^2 + 0^2 + 0^2 + 0^2) | F5: =SQRT(0^2 + 0^2 + 0^2 + 0^2)
B6: Owner | C6: Owner | D6: Owner | E6: =0 | F6: =0
B7: Physician | C7: Physician | D7: Physician | E7: =0 | F7: =0
B8: Appointment | C8: Appointment | D8: Appointment | E8: =0 | F8: =0
B9: Appointment .Date | C9: Appointment .StartDate | D9: Appointment .DateandTime | E9: =SQRT(0^2 + 0^2 + 1^2 + 0^2) | F9: =SQRT(0^2 + 0^2 + 1^2 + 0^2)
B10: Appointment .Time | C10: Appointment .StartTime | D10: \ | E10: =SQRT(0^2 + 0^2 + 1^2 + 0^2) | F10: =SQRT(1^2 + 1^2 + 1^2 + 1^2)
B11: Condition | C11: Medical_Condition | D11: Medical_Condition | E11: =0.5 | F11: =0.5
B12: Condition .Common_Name | C12: Medical_Condition .CommonName | D12: Medical_Condition .CommonName | E12: =SQRT(0^2 + 0^2 + 0^2 + 0^2) | F12: =SQRT(0^2 + 0^2 + 0^2 + 0^2)
B13: Condition .Sci_Name | C13: Medical_Condition .ScientificName | D13: Medical_Condition .ScientificName | E13: =SQRT(0^2 + 0^2 + 0^2 + 0^2) | F13: =SQRT(0^2 + 0^2 + 0^2 + 0^2)
B14: Breed | C14: Breed | D14: Breed | E14: =0 | F14: =0
B15: Breed .Name | C15: Breed .Type | D15: Breed .Name | E15: =SQRT(0^2 + 0^2 + 1^2 + 0^2) | F15: =SQRT(0^2 + 0^2 + 0^2 + 0^2)
B16: Person | C16: \ | D16: \ | E16: =1 | F16: 1
B17: Person .ID | C17: Owner/Physician .ID | D17: Owner/Physician .ID | E17: =SQRT(0^2 + 0^2 + 0^2 + 0^2) | F17: =SQRT(0^2 + 0^2 + 0^2 + 0^2)
B18: Person .Name | C18: Owner/Physician .Name | D18: Owner/Physician .Name | E18: =SQRT(0^2 + 0^2 + 0^2 + 0^2) | F18: =SQRT(0^2 + 0^2 + 0^2 + 0^2)
B19: Person .Address | C19: Owner/Physician .Address | D19: Owner/Physician .Address | E19: =SQRT(0^2 + 0^2 + 0^2 + 0^2) | F19: =SQRT(0^2 + 0^2 + 0^2 + 0^2)
B20: Person .Phone | C20: Owner/Physician .PhoneNumber | D20: Owner/Physician .PhoneNumber | E20: =SQRT(0^2 + 0^2 + 1^2 + 0^2) | F20: =SQRT(0^2 + 0^2 + 1^2 + 0^2)
B21: Association (Animal - Owner) | C21: Association (Animal - Owner) | D21: Association (Animal - Owner) | E21: =SQRT(0^2 + 0^2 + 0^2 + 0^2) | F21: =SQRT(0^2 + 0^2 + 0^2 + 1^2)
B22: Association (Animal - Breed) | C22: Association (Animal - Breed) | D22: Association (Animal - Breed) | E22: =SQRT(0^2 + 0^2 + 0^2 + 0^2) | F22: =SQRT(0^2 + 0^2 + 0^2 + 0^2)
B23: Association (Animal - Appointment) | C23: Association (Animal - Appointment) | D23: Association (Animal - Appointment) | E23: =SQRT(0^2 + 0^2 + 0^2 + 0^2) | F23: =SQRT(0^2 + 0^2 + 0^2 + 0^2)
B24: Association (Appointment - Condition) | C24: Association (Appointment - Medical_Condition) | D24: \ | E24: =SQRT(0^2 + 0^2 + 0^2 + 0^2) | F24: =SQRT(1^2 + 1^2 + 1^2 + 1^2)
B25: Association (Breed - Condition) | C25: Association (Breed - Medical_Condition) | D25: Association (Breed - Medical_Condition) | E25: =SQRT(0^2 + 0^2 + 0^2 + 0^2) | F25: =SQRT(0^2 + 0^2 + 0^2 + 0^2)
B26: Association (Appointment - Physician) | C26: Association (Appointment - Physician) | D26: Association (Appointment - Physician) | E26: =SQRT(0^2 + 0^2 + 0^2 + 0^2) | F26: =SQRT(0^2 + 0^2 + 0^2 + 0^2)
B27: Generalization (Owner - Person) | C27: \ | D27: \ | E27: =SQRT(1^2 + 1^2 + 1^2 + 1^2) | F27: =SQRT(1^2 + 1^2 + 1^2 + 1^2)
B28: Generalizzation (Physician - Person) | C28: \ | D28: \ | E28: =SQRT(1^2 + 1^2 + 1^2 + 1^2) | F28: =SQRT(1^2 + 1^2 + 1^2 + 1^2)
B29: \ | C29: Association (Appointment - Owner) | D29: \ | E29: =SQRT(1^2 + 1^2 + 1^2 + 1^2) | F29: =SQRT(0^2 + 0^2 + 0^2 + 0^2)
D32: Total Distance | E32: =SQRT(SUMSQ(E3:E29)) | F32: =SQRT(SUMSQ(F3:F29))

Sheet Part 2 - 9
B2: Given Solution | C2: Human | D2: LLM | E2: Distance Human | F2: Distance LLM
B3: Person | C3: \ | D3: \ | E3: =1 | F3: =1
B4: Person .ID | C4: Employee/Owner .ID | D4: Owner/Employee .ID | E4: =SQRT(0^2 + 0^2 + 0^2 + 0^2) | F4: =SQRT(0^2 + 0^2 + 0^2 + 0^2)
B5: Person .Name | C5: Employee/Owner .Name | D5: Owner/Employee .Name | E5: =SQRT(0^2 + 0^2 + 0^2 + 0^2) | F5: =SQRT(0^2 + 0^2 + 0^2 + 0^2)
B6: Person .Address | C6: Employee/Owner .Address | D6: Owner/Employee .Address | E6: =SQRT(0^2 + 0^2 + 0^2 + 0^2) | F6: =SQRT(0^2 + 0^2 + 0^2 + 0^2)
B7: Employee | C7: Employee | D7: Employee | E7: =0 | F7: =0
B8: Owner | C8: Owner | D8: Owner | E8: =0 | F8: =0
B9: \ | C9: Owner .Phone | D9: Owner .PhoneNumber | E9: =SQRT(1^2 + 1^2 + 1^2 + 1^2) | F9: =SQRT(1^2 + 1^2 + 1^2 + 1^2)
B10: Service | C10: Assembly_Service | D10: AssemblyService | E10: =0.5 | F10: =0.5
B11: Service .Car_Km | C11: Assembly_Service .kmscar | D11: \ | E11: =SQRT(0^2 + 0^2 + 0^2 + 0^2) | F11: =SQRT(1^2 + 1^2 + 1^2 + 1^2)
B12: Service .Hours_spent | C12: Assembly_Service .workhours | D12: AssemblyService .workhours | E12: =SQRT(0^2 + 0^2 + 1^2 + 0^2) | F12: =SQRT(0^2 + 0^2 + 1^2 + 0^2)
B13: Service .Adm_Date | C13: Assembly_Service .AdmissionDate | D13: AssemblyService .AdmissionDate | E13: =SQRT(0^2 + 0^2 + 0^2 + 0^2) | F13: =SQRT(0^2 + 0^2 + 0^2 + 0^2)
B14: Service .Finish_Date | C14: Assembly_Service .FinishDate | D14: AssemblyService .FinishDate | E14: =SQRT(0^2 + 0^2 + 0^2 + 0^2) | F14: =SQRT(0^2 + 0^2 + 0^2 + 0^2)
B15: Part/Acc | C15: Part/Accessory | D15: PartAccessory | E15: =0 | F15: =0
B16: Part/Acc .Serial_No | C16: Part/Accessory .SerialNumber | D16: PartAccessory .SerialNumber | E16: =SQRT(0^2 + 0^2 + 0^2 + 0^2) | F16: =SQRT(0^2 + 0^2 + 0^2 + 0^2)
B17: Part/Acc .Price | C17: Part/Accessory .Price | D17: PartAccessory .Price | E17: =SQRT(0^2 + 0^2 + 0^2 + 0^2) | F17: =SQRT(0^2 + 0^2 + 0^2 + 0^2)
B18: \ | C18: Part/Accessory .category | D18: PartAccessory .Category | E18: =SQRT(1^2 + 1^2 + 1^2 + 1^2) | F18: =SQRT(1^2 + 1^2 + 1^2 + 1^2)
B19: Part Type | C19: \ | D19: \ | E19: =1 | F19: =1
B20: Part Type .Current_Price | C20: \ | D20: \ | E20: =SQRT(1^2 + 1^2 + 1^2 + 1^2) | F20: =SQRT(1^2 + 1^2 + 1^2 + 1^2)
B21: Car | C21: Car | D21: Car | E21: =SQRT(0^2 + 0^2 + 0^2 + 0^2) | F21: =0
B22: Car .Plate | C22: Car .Plate | D22: Car .LicensePlate | E22: =SQRT(0^2 + 0^2 + 0^2 + 0^2) | F22: =SQRT(0^2 + 0^2 + 1^2 + 0^2)
B23: Car .Color | C23: Car .Color | D23: Car .Color | E23: =SQRT(0^2 + 0^2 + 0^2 + 0^2) | F23: =SQRT(0^2 + 0^2 + 0^2 + 0^2)
B24: \ | C24: Car .Model | D24: Car .Model | E24: =SQRT(1^2 + 1^2 + 1^2 + 1^2) | F24: =SQRT(1^2 + 1^2 + 1^2 + 1^2)
B25: Car Model | C25: \ | D25: Car Model | E25: =1 | F25: =0
B26: \ | C26: Car .Make | D26: Car Model .Make | E26: =SQRT(1^2 + 1^2 + 1^2 + 1^2) | F26: =SQRT(1^2 + 1^2 + 1^2 + 1^2)
B27: Make | C27: \ | D27: \ | E27: 1 | F27: =1
B28: Make .Name | C28: \ | D28: \ | E28: =SQRT(1^2 + 1^2 + 1^2 + 1^2) | F28: =SQRT(1^2 + 1^2 + 1^2 + 1^2)
B29: Generalization (Employee - Person) | C29: \ | D29: \ | E29: =SQRT(1^2 + 1^2 + 1^2 + 1^2) | F29: =SQRT(1^2 + 1^2 + 1^2 + 1^2)
B30: Generalization (Owner - Person) | C30: \ | D30: \ | E30: =SQRT(1^2 + 1^2 + 1^2 + 1^2) | F30: =SQRT(1^2 + 1^2 + 1^2 + 1^2)
B31: Association ( Employee - Service) | C31: Association (Employee - Assembly Service) | D31: Association (Employee - Assembly Service) | E31: =SQRT(0^2 + 0^2 + 0^2 + 0^2) | F31: =SQRT(0^2 + 0^2 + 0^2 + 0^2)
B32: Association (Owner - Car) | C32: Association (Owner - Car) | D32: Association (Owner - Car) | E32: =SQRT(0^2 + 0^2 + 0^2 + 1^2) | F32: =SQRT(0^2 + 0^2 + 0^2 + 1^2)
B33: Association (Service - Part/Acc) | C33: Association (Assembly Service - Part/Accessory) | D33: Association (Assembly Service - PartAccessory) | E33: =SQRT(0^2 + 0^2 + 0^2 + 0^2) | F33: =SQRT(0^2 + 0^2 + 0^2 + 1^2)
B34: Association (Car - Car Model) | C34: \ | D34: \ | E34: =SQRT(1^2 + 1^2 + 1^2 + 1^2) | F34: =SQRT(1^2 + 1^2 + 1^2 + 1^2)
B35: Association (Service - Car) | C35: Association (Assembly Service - Car) | D35: Association (Assembly Service - Car) | E35: =SQRT(0^2 + 0^2 + 0^2 + 0^2) | F35: =SQRT(0^2 + 0^2 + 0^2 + 0^2)
B36: Association (Car Model - Make) | C36: \ | D36: \ | E36: =SQRT(1^2 + 1^2 + 1^2 + 1^2) | F36: =SQRT(1^2 + 1^2 + 1^2 + 1^2)
B37: Association (Part/Acc - Part Type) | C37: \ | D37: \ | E37: =SQRT(1^2 + 1^2 + 1^2 + 1^2) | F37: =SQRT(1^2 + 1^2 + 1^2 + 1^2)
B38: Association (Car Model - Part Type) | C38: \ | D38: \ | E38: =SQRT(1^2 + 1^2 + 1^2 + 1^2) | F38: =SQRT(1^2 + 1^2 + 1^2 + 1^2)
B39: \ | C39: Association (Part/Accessory - Car) | D39: \ | E39: =SQRT(0^2 + 0^2 + 0^2 + 0^2) | F39: =SQRT(0^2 + 0^2 + 0^2 + 0^2)
B40: \ | C40: \ | D40: Association (PartAccessory - CarModel) | E40: =SQRT(1^2 + 1^2 + 1^2 + 1^2) | F40: =SQRT(1^2 + 1^2 + 1^2 + 1^2)
D43: Total Distance | E43: =SQRT(SUMSQ(E3:E40)) | F43: =SQRT(SUMSQ(F3:F40))

Sheet Part 2 - 10
B2: Given Solution | C2: Human | D2: LLM | E2: Distance Human | F2: Distance LLM
B3: Person | C3: \ | D3: \ | E3: =1 | F3: =1
B4: Person .Name | C4: Client/Waiter .Name | D4: Client/Waiter .Name | E4: =SQRT(0^2 + 0^2 + 0^2 + 0^2) | F4: =SQRT(0^2 + 0^2 + 0^2 + 0^2)
B5: Person .Address | C5: Client/Waiter .Address | D5: Client/Waiter .Address | E5: =SQRT(0^2 + 0^2 + 0^2 + 0^2) | F5: =SQRT(0^2 + 0^2 + 0^2 + 0^2)
B6: Client | C6: Client | D6: Client | E6: =0 | F6: =0
B7: Client .Tax_ID | C7: Client .Tax_ID | D7: Client .Tax_ID | E7: =SQRT(0^2 + 0^2 + 0^2 + 0^2) | F7: =SQRT(0^2 + 0^2 + 0^2 + 0^2)
B8: Waiter | C8: Waiter | D8: Waiter | E8: =0 | F8: =0
B9: Waiter .ID | C9: Waiter .ID | D9: Waiter .ID | E9: =SQRT(0^2 + 0^2 + 0^2 + 0^2) | F9: =SQRT(0^2 + 0^2 + 0^2 + 0^2)
B10: Waiter .Phone | C10: Waiter .PhoneNumber | D10: Waiter .PhoneNumber | E10: =SQRT(0^2 + 0^2 + 0^2 + 0^2) | F10: =SQRT(0^2 + 0^2 + 0^2 + 0^2)
B11: Meal | C11: Meal | D11: Meal | E11: =0 | F11: =0
B12: Meal .Date | C12: Meal .Date | D12: \ | E12: =SQRT(0^2 + 0^2 + 0^2 + 0^2) | F12: =SQRT(1^2 + 1^2 + 1^2 + 1^2)
B13: Meal .StartTime | C13: Meal .StartTime | D13: Meal .StartDate | E13: =SQRT(0^2 + 0^2 + 0^2 + 0^2) | F13: =SQRT(0^2 + 0^2 + 1^2 + 1^2)
B14: Meal .EndTime | C14: Meal .EndTime | D14: Meal .EndDate | E14: =SQRT(0^2 + 0^2 + 0^2 + 0^2) | F14: =SQRT(0^2 + 0^2 + 1^2 + 1^2)
B15: Table | C15: Table | D15: Table | E15: =0 | F15: =0
B16: Table .ID | C16: Table .ID | D16: Table .ID | E16: =SQRT(0^2 + 0^2 + 0^2 + 0^2) | F16: =SQRT(0^2 + 0^2 + 0^2 + 0^2)
B17: Table .Capacity | C17: Table .nofpeople | D17: Table .MaxCapacity | E17: =SQRT(0^2 + 0^2 + 1^2 + 0^2) | F17: =SQRT(0^2 + 0^2 + 0^2 + 0^2)
B18: Dish | C18: Dish | D18: Dish | E18: =0 | F18: =0
B19: Dish .ID | C19: DIsh .ID | D19: DIsh .ID | E19: =SQRT(0^2 + 0^2 + 0^2 + 0^2) | F19: =SQRT(0^2 + 0^2 + 0^2 + 0^2)
B20: Dish .Name | C20: DIsh .Name | D20: DIsh .Name | E20: =SQRT(0^2 + 0^2 + 0^2 + 0^2) | F20: =SQRT(0^2 + 0^2 + 0^2 + 0^2)
B21: Ingredient | C21: Ingredient | D21: Ingredient | E21: =0 | F21: =0
B22: Ingredient .Name | C22: Ingredient .Name | D22: Ingredient .Name | E22: =SQRT(0^2 + 0^2 + 0^2 + 0^2) | F22: =SQRT(0^2 + 0^2 + 0^2 + 0^2)
B23: Ingredient .Unit | C23: Ingredient .MeasuringUnits | D23: Ingredient .MeasuringUnit | E23: =SQRT(0^2 + 0^2 + 1^2 + 0^2) | F23: =SQRT(0^2 + 0^2 + 1^2 + 0^2)
B24: Ingredient .Stock | C24: Ingredient .Quantity | D24: Ingredient .QuantityinStock | E24: =SQRT(0^2 + 0^2 + 1^2 + 0^2) | F24: =SQRT(0^2 + 0^2 + 1^2 + 0^2)
B25: Generalization (Person - Client) | C25: \ | D25: \ | E25: =SQRT(1^2 + 1^2 + 1^2 + 1^2) | F25: =SQRT(1^2 + 1^2 + 1^2 + 1^2)
B26: Generalization (Person - Waiter) | C26: \ | D26: \ | E26: =SQRT(1^2 + 1^2 + 1^2 + 1^2) | F26: =SQRT(1^2 + 1^2 + 1^2 + 1^2)
B27: Association (Client - Meal) | C27: Association (Client - Meal) | D27: Association (Client - Meal) | E27: =SQRT(0^2 + 0^2 + 0^2 + 0^2) | F27: =SQRT(0^2 + 0^2 + 0^2 + 0^2)
B28: Association (Waiter - Meal) | C28: Association (Waiter - Meal) | D28: Association (Waiter - Meal) | E28: =SQRT(0^2 + 0^2 + 0^2 + 0^2) | F28: =SQRT(0^2 + 0^2 + 0^2 + 0^2)
B29: Association (Meal - Table) | C29: Association (Meal - Table) | D29: Association (Meal - Table) | E29: =SQRT(0^2 + 0^2 + 0^2 + 0^2) | F29: =SQRT(0^2 + 0^2 + 0^2 + 0^2)
B30: Association (Meal - Dish) | C30: Association (Meal - Dish) | D30: Association (Meal - Dish) | E30: =SQRT(0^2 + 0^2 + 0^2 + 1^2) | F30: =SQRT(0^2 + 0^2 + 0^2 + 1^2)
B31: Association (Dish - Ingredient) | C31: Association (Dish - Ingredient) | D31: Association (Dish - Ingredient) | E31: =SQRT(0^2 + 0^2 + 0^2 + 0^2) | F31: =SQRT(0^2 + 0^2 + 0^2 + 1^2)
D34: Total Distance | E34: =SQRT(SUMSQ(E3:E31)) | F34: =SQRT(SUMSQ(F3:F31))

Sheet Part 2 - 11
B2: Given Solution | C2: Human | D2: LLM | E2: Distance Human | F2: Distance LLM
B3: Person | C3: \ | D3: \ | E3: =1 | F3: =1
B4: Person .VAT | C4: Customer/Courier .VAT | D4: Customer/Courier .VATNumber | E4: =SQRT(0^2 + 0^2 + 0^2 + 0^2) | F4: =SQRT(0^2 + 0^2 + 0^2 + 0^2)
B5: Person .Name | C5: Customer/Courier .Name | D5: Customer/Courier .Name | E5: =SQRT(0^2 + 0^2 + 0^2 + 0^2) | F5: =SQRT(0^2 + 0^2 + 0^2 + 0^2)
B6: Person .Phone | C6: Customer/Courier .Phone | D6: Customer/Courier .PhoneNumber | E6: =SQRT(0^2 + 0^2 + 0^2 + 0^2) | F6: =SQRT(0^2 + 0^2 + 0^2 + 0^2)
B7: Customer | C7: Customer | D7: Customer | E7: =0 | F7: =0
B8: Customer .Address | C8: Customer .Address | D8: Customer .Address | E8: =SQRT(0^2 + 0^2 + 0^2 + 0^2) | F8: =SQRT(0^2 + 0^2 + 0^2 + 0^2)
B9: Package | C9: Package | D9: Package | E9: =0 | F9: =0
B10: Package .ID | C10: Package .ID | D10: Package .identifierCode | E10: =SQRT(0^2 + 0^2 + 0^2 + 0^2) | F10: =SQRT(0^2 + 0^2 + 1^2 + 0^2)
B11: Package .Weight | C11: Package .Weight | D11: Package .Weight | E11: =SQRT(0^2 + 0^2 + 0^2 + 0^2) | F11: =SQRT(0^2 + 0^2 + 0^2 + 0^2)
B12: Package .Urgency | C12: Package .Urgent | D12: Package .DeliveryType | E12: =SQRT(0^2 + 0^2 + 0^2 + 0^2) | F12: =SQRT(0^2 + 0^2 + 1^2 + 1^2)
B13: Courier | C13: Courier | D13: Courier | E13: =0 | F13: =0
B14: DeliveryCenter | C14: DeliveryCenter | D14: DeliveryCenter | E14: =0 | F14: =0
B15: DeliveryCenter .Name | C15: DeliveryCenter .Name | D15: DeliveryCenter .Name | E15: =SQRT(0^2 + 0^2 + 0^2 + 0^2) | F15: =SQRT(0^2 + 0^2 + 0^2 + 0^2)
B16: DeliveryCenter .Address | C16: DeliveryCenter .Address | D16: DeliveryCenter .Address | E16: =SQRT(0^2 + 0^2 + 0^2 + 0^2) | F16: =SQRT(0^2 + 0^2 + 0^2 + 0^2)
B17: Generalization (Person - Customer) | C17: \ | D17: \ | E17: =SQRT(1^2 + 1^2 + 1^2 + 1^2) | F17: =SQRT(1^2 + 1^2 + 1^2 + 1^2)
B18: Generalization (Person - Courier) | C18: \ | D18: \ | E18: =SQRT(1^2 + 1^2 + 1^2 + 1^2) | F18: =SQRT(1^2 + 1^2 + 1^2 + 1^2)
B19: Association (Courier - DeliveryCenter) | C19: Association (Courier - DeliveryCenter) | D19: Association (Courier - DeliveryCenter) | E19: =SQRT(0^2 + 0^2 + 0^2 + 0^2) | F19: =SQRT(0^2 + 0^2 + 0^2 + 0^2)
B20: Association (Courier - Package) | C20: Association (Courier - Package) | D20: Association (Courier - Package) | E20: =SQRT(0^2 + 0^2 + 0^2 + 0^2) | F20: =SQRT(0^2 + 0^2 + 0^2 + 1^2)
B21: Association (Customer - DeliveryCenter) | C21: Association (Customer - DeliveryCenter) | D21: Association (Customer - DeliveryCenter) 1 | E21: =SQRT(0^2 + 0^2 + 0^2 + 0^2) | F21: =SQRT(0^2 + 0^2 + 0^2 + 0^2)
B22: Association (Customer - Package) 1 | C22: Association (Customer - Package) | D22: Association (Customer - Package) 1 | E22: =SQRT(0^2 + 0^2 + 0^2 + 1^2) | F22: =SQRT(0^2 + 0^2 + 0^2 + 0^2)
B23: Association (Customer - Package) 2 | C23: \ | D23: Association (Customer - Package) 2 | E23: =SQRT(1^2 + 1^2 + 1^2 + 1^2) | F23: =SQRT(0^2 + 0^2 + 0^2 + 0^2)
B24: Association (DeliveryCenter - Package) 1 | C24: Association (DeliveryCenter - Package) | D24: \ | E24: =SQRT(0^2 + 0^2 + 0^2 + 1^2) | F24: =SQRT(1^2 + 1^2 + 1^2 + 1^2)
B25: Association (DeliveryCenter - Package) 2 | C25: \ | D25: \ | E25: =SQRT(1^2 + 1^2 + 1^2 + 1^2) | F25: =SQRT(1^2 + 1^2 + 1^2 + 1^2)
B26: \ | C26: Association (Courier - Customer) | D26: \ | E26: =SQRT(1^2 + 1^2 + 1^2 + 1^2) | F26: =SQRT(0^2 + 0^2 + 0^2 + 0^2)
B27: \ | C27: Association (Customer - Customer) | D27: \ | E27: =SQRT(1^2 + 1^2 + 1^2 + 1^2) | F27: =SQRT(0^2 + 0^2 + 0^2 + 0^2)
B28: \ | C28: \ | D28: Association (Customer - DeliveryCenter) 2 | E28: =SQRT(0^2 + 0^2 + 0^2 + 0^2) | F28: =SQRT(1^2 + 1^2 + 1^2 + 1^2)
D31: Total Distance | E31: =SQRT(SUMSQ(E3:E28)) | F31: =SQRT(SUMSQ(F3:F28))

Sheet Part 2 - 12
B2: Given Solution | C2: Human | D2: LLM | E2: Distance Human | F2: Distance LLM
B3: Store | C3: Store | D3: Store | E3: =0 | F3: =0
B4: Store .Name | C4: \ | D4: \ | E4: =SQRT(1^2 + 1^2 + 1^2 + 1^2) | F4: =SQRT(1^2 + 1^2 + 1^2 + 1^2)
B5: Store .Address | C5: Store .Address | D5: Store .Address | E5: =SQRT(0^2 + 0^2 + 0^2 + 0^2) | F5: =SQRT(0^2 + 0^2 + 0^2 + 0^2)
B6: Store .FAX | C6: Store .FAX | D6: Store .FAXnumber | E6: =SQRT(0^2 + 0^2 + 0^2 + 0^2) | F6: =SQRT(0^2 + 0^2 + 0^2 + 0^2)
B7: Order | C7: Order | D7: Order | E7: =0 | F7: =0
B8: Order .Number | C8: Order .Number | D8: Order .OrderNumber | E8: =SQRT(0^2 + 0^2 + 0^2 + 0^2) | F8: =SQRT(0^2 + 0^2 + 0^2 + 0^2)
B9: Order .Date | C9: Order .Date | D9: Order .Date | E9: =SQRT(0^2 + 0^2 + 0^2 + 0^2) | F9: =SQRT(0^2 + 0^2 + 0^2 + 0^2)
B10: Piece | C10: Piece of Furniture | D10: FurniturePiece | E10: =0.5 | F10: =0.5
B11: Piece .Ref | C11: Piece of Furniture .Reference | D11: FurniturePiece .Reference | E11: =SQRT(0^2 + 0^2 + 0^2 + 0^2) | F11: =SQRT(0^2 + 0^2 + 0^2 + 0^2)
B12: Piece .Price | C12: Piece of Furniture .Price | D12: FurniturePiece .SellingPrice | E12: =SQRT(0^2 + 0^2 + 0^2 + 0^2) | F12: =SQRT(0^2 + 0^2 + 1^2 + 0^2)
B13: \ | C13: Piece of Furniture .type | D13: FurniturePiece .Type | E13: =SQRT(1^2 + 1^2 + 1^2 + 1^2) | F13: =SQRT(1^2 + 1^2 + 1^2 + 1^2)
B14: Line | C14: Furniture Line | D14: Furniture Line | E14: =0.5 | F14: =0.5
B15: Line .Type | C15: Furniture Line .Name | D15: Furniture Line .Name | E15: =SQRT(0^2 + 0^2 + 1^2 + 0^2) | F15: =SQRT(0^2 + 0^2 + 1^2 + 0^2)
B16: Component | C16: Component | D16: Component | E16: =0 | F16: =0
B17: Component .Code | C17: Component .NumericalCode | D17: Component .NumericalCode | E17: =SQRT(0^2 + 0^2 + 0^2 + 0^2) | F17: =SQRT(0^2 + 0^2 + 0^2 + 0^2)
B18: Component .Price | C18: Component .Price | D18: Component .ManufacturingPrice | E18: =SQRT(0^2 + 0^2 + 0^2 + 0^2) | F18: =SQRT(0^2 + 0^2 + 1^2 + 0^2)
B19: \ | C19: \ | D19: Component .Type | E19: =SQRT(0^2 + 0^2 + 0^2 + 0^2) | F19: =SQRT(1^2 + 1^2 + 1^2 + 1^2)
B20: ComponentType | C20: ComponentType | D20: \ | E20: =0 | F20: =SQRT(1^2 + 1^2 + 1^2 + 1^2)
B21: ComponentType .Name | C21: ComponentType .Name | D21: \ | E21: =SQRT(0^2 + 0^2 + 0^2 + 0^2) | F21: =SQRT(1^2 + 1^2 + 1^2 + 1^2)
B22: Association (Store - Order) | C22: Association (Store - Order) | D22: Association (Store - Order) | E22: =SQRT(0^2 + 0^2 + 0^2 + 0^2) | F22: =SQRT(0^2 + 0^2 + 0^2 + 0^2)
B23: Association (Order - Piece) | C23: Association (Order - Piece of Furniture) | D23: Association (Order - FurniturePiece) | E23: =SQRT(0^2 + 0^2 + 0^2 + 0^2) | F23: =SQRT(0^2 + 0^2 + 0^2 + 0^2)
B24: Association (Piece - Line) | C24: Association (Piece of Furniture - Furniture Line) | D24: Association (FurniturePiece - Furniture Line) | E24: =SQRT(0^2 + 0^2 + 0^2 + 0^2) | F24: =SQRT(0^2 + 0^2 + 0^2 + 0^2)
B25: Association (Piece - Component) | C25: Association (Piece of Furniture - Component) | D25: Association (FurniturePiece - Component) | E25: =SQRT(0^2 + 0^2 + 0^2 + 0^2) | F25: =SQRT(0^2 + 0^2 + 0^2 + 1^2)
B26: Association (Component - ComponentType) | C26: Association (Component - ComponentType) | D26: \ | E26: =SQRT(0^2 + 0^2 + 0^2 + 0^2) | F26: =SQRT(1^2 + 1^2 + 1^2 + 1^2)
B27: \ | C27: Association (Piece of Furniture - Store) | D27: \ | E27: =SQRT(1^2 + 1^2 + 1^2 + 1^2) | F27: 0
D30: Total Distance | E30: =SQRT(SUMSQ(E3:E27)) | F30: =SQRT(SUMSQ(F3:F27))

Sheet Part 2 - 13
B2: Given Solution | C2: Human | D2: LLM | E2: Distance Human | F2: Distance LLM
B3: Person | C3: \ | D3: \ | E3: =1 | F3: =1
B4: Person .FirstName | C4: Worker .FirstName | D4: Worker .Name | E4: =SQRT(0^2 + 0^2 + 0^2 + 0^2) | F4: =SQRT(0^2 + 0^2 + 1^2 + 0^2)
B5: Person .Surname | C5: Worker .LastName | D5: \ | E5: =SQRT(0^2 + 0^2 + 0^2 + 0^2) | F5: =SQRT(1^2 + 1^2 + 1^2 + 1^2)
B6: Person .Address | C6: Worker/Client .Address | D6: Worker/Client .Address | E6: =SQRT(0^2 + 0^2 + 0^2 + 0^2) | F6: =SQRT(0^2 + 0^2 + 0^2 + 0^2)
B7: Client | C7: Client | D7: Client | E7: =0 | F7: =0
B8: Client .Phone | C8: Client .Phone | D8: Client .PhoneNumber | E8: =SQRT(0^2 + 0^2 + 0^2 + 0^2) | F8: =SQRT(0^2 + 0^2 + 0^2 + 0^2)
B9: Client .Contact_Person | C9: Client .Contact_Person | D9: Client .Contact_Person | E9: =SQRT(0^2 + 0^2 + 0^2 + 0^2) | F9: =SQRT(0^2 + 0^2 + 0^2 + 0^2)
B10: \ | C10: Client. Name | D10: Client. Name | E10: =SQRT(1^2 + 1^2 + 1^2 + 1^2) | F10: =SQRT(1^2 + 1^2 + 1^2 + 1^2)
B11: Worker | C11: Worker | D11: Worker | E11: =0 | F11: =0
B12: Worker .Birth_Date | C12: Worker .Birth_Date | D12: Worker .BirthDate | E12: =SQRT(0^2 + 0^2 + 0^2 + 0^2) | F12: =SQRT(0^2 + 0^2 + 0^2 + 0^2)
B13: Skill | C13: Skill | D13: \ | E13: =0 | F13: =1
B14: Skill .Name | C14: Skill .Name | D14: Worker .Skills | E14: =SQRT(0^2 + 0^2 + 0^2 + 0^2) | F14: =SQRT(0^2 + 0^2 + 1^2 + 1^2)
B15: Machine | C15: Machine | D15: Machine | E15: =0 | F15: =0
B16: Machine .Serial | C16: Machine .SerialNumber | D16: Machine .SerialNumber | E16: =SQRT(0^2 + 0^2 + 0^2 + 0^2) | F16: =SQRT(0^2 + 0^2 + 0^2 + 0^2)
B17: Machine .Make | C17: Machine .Make | D17: Machine .Make | E17: =SQRT(0^2 + 0^2 + 0^2 + 0^2) | F17: =SQRT(0^2 + 0^2 + 0^2 + 0^2)
B18: Machine .Model | C18: Machine .Model | D18: Machine .Model | E18: =SQRT(0^2 + 0^2 + 0^2 + 0^2) | F18: =SQRT(0^2 + 0^2 + 0^2 + 0^2)
B19: Machine .Purchase_Date | C19: Machine .Purchase_Date | D19: Machine .Purchase_Date | E19: =SQRT(0^2 + 0^2 + 0^2 + 0^2) | F19: =SQRT(0^2 + 0^2 + 0^2 + 0^2)
B20: Product_Type | C20: Product_Type | D20: Product_Type | E20: =0 | F20: =0
B21: Product_Type .Material | C21: Product_Type .Material | D21: Product_Type .Material | E21: =SQRT(0^2 + 0^2 + 0^2 + 0^2) | F21: =SQRT(0^2 + 0^2 + 0^2 + 0^2)
B22: Product_Type .Weight | C22: Product_Type .Weight | D22: Product_Type .Weight | E22: =SQRT(0^2 + 0^2 + 0^2 + 0^2) | F22: =SQRT(0^2 + 0^2 + 0^2 + 0^2)
B23: Product | C23: Product | D23: Product | E23: =0 | F23: =0
B24: Product .ID | C24: Product .ID | D24: Product .ID | E24: =SQRT(0^2 + 0^2 + 0^2 + 0^2) | F24: =SQRT(0^2 + 0^2 + 0^2 + 0^2)
B25: Product .Name | C25: Product .Name | D25: \ | E25: =SQRT(0^2 + 0^2 + 0^2 + 0^2) | F25: =SQRT(1^2 + 1^2 + 1^2 + 1^2)
B26: Purchase Order | C26: Order | D26: Purchase Order | E26: =0.5 | F26: =0
B27: Purchase Order .Number | C27: Order .Number | D27: Purchase Order .OrderNumber | E27: =SQRT(0^2 + 0^2 + 0^2 + 0^2) | F27: =SQRT(0^2 + 0^2 + 0^2 + 0^2)
B28: Purchase Order .Date | C28: Order .Date | D28: Purchase Order. dateMade | E28: =SQRT(0^2 + 0^2 + 0^2 + 0^2) | F28: =SQRT(0^2 + 0^2 + 0^2 + 0^2)
B29: Purchase Order .Expected_Del | C29: Order .Expected_Delivery_Date | D29: Purchase Order .ExpectedDeliveryDate | E29: =SQRT(0^2 + 0^2 + 0^2 + 0^2) | F29: =SQRT(0^2 + 0^2 + 0^2 + 0^2)
B30: Purchase Order .Actual_Del | C30: Order .Actual_Delivery_Date | D30: Purchase Order .ActualDeliveryDate | E30: =SQRT(0^2 + 0^2 + 0^2 + 0^2) | F30: =SQRT(0^2 + 0^2 + 0^2 + 0^2)
B31: Generalization (Person - Client) | C31: \ | D31: \ | E31: =SQRT(1^2 + 1^2 + 1^2 + 1^2) | F31: =SQRT(1^2 + 1^2 + 1^2 + 1^2)
B32: Generalization (Person - Worker) | C32: \ | D32: \ | E32: =SQRT(1^2 + 1^2 + 1^2 + 1^2) | F32: =SQRT(1^2 + 1^2 + 1^2 + 1^2)
B33: Association ( Client - Purchase Order) | C33: Association ( Client - Order) | D33: Association (Client - Purchase Order) | E33: =SQRT(0^2 + 0^2 + 0^2 + 0^2) | F33: =SQRT(0^2 + 0^2 + 0^2 + 0^2)
B34: Association (Worker - Skill) | C34: Association (Worker - Skill) | D34: \ | E34: =SQRT(0^2 + 0^2 + 0^2 + 0^2) | F34: =SQRT(1^2 + 1^2 + 1^2 + 1^2)
B35: Association (Worker - Machine) | C35: Association (Worker - Machine) | D35: Association (Worker - Machine) | E35: =SQRT(0^2 + 0^2 + 0^2 + 0^2) | F35: =SQRT(0^2 + 0^2 + 0^2 + 1^2)
B36: Association (Machine - Product_Type) | C36: Association (Machine - Product_Type) | D36: \ | E36: =SQRT(0^2 + 0^2 + 0^2 + 0^2) | F36: =SQRT(1^2 + 1^2 + 1^2 + 1^2)
B37: Association (Product_Type - Product) | C37: Association (Product_Type - Product) | D37: Association (Product_Type - Product) | E37: =SQRT(0^2 + 0^2 + 0^2 + 0^2) | F37: =SQRT(0^2 + 0^2 + 0^2 + 0^2)
B38: Association (Product - Purchase Order) | C38: Association (Product - Order) | D38: Association (Product - Purchase Order) | E38: =SQRT(0^2 + 0^2 + 0^2 + 0^2) | F38: =SQRT(0^2 + 0^2 + 0^2 + 0^2)
B39: \ | C39: \ | D39: Association (Worker - Product) | E39: =SQRT(0^2 + 0^2 + 0^2 + 0^2) | F39: =SQRT(1^2 + 1^2 + 1^2 + 1^2)
D42: Total Distance | E42: =SQRT(SUMSQ(E3:E39)) | F42: =SQRT(SUMSQ(F3:F39))

Sheet Part 2 - 14
B2: Given Solution | C2: Human | D2: LLM | E2: Distance Human | F2: Distance LLM
B3: Client | C3: Client | D3: Client | E3: =0 | F3: =0
B4: Client .Nin | C4: Client .Nin | D4: Client .Nin | E4: =SQRT(0^2 + 0^2 + 0^2 + 0^2) | F4: =SQRT(0^2 + 0^2 + 0^2 + 0^2)
B5: Client .Tin | C5: Client .Tin | D5: Client .Tin | E5: =SQRT(0^2 + 0^2 + 0^2 + 0^2) | F5: =SQRT(0^2 + 0^2 + 0^2 + 0^2)
B6: Client. Name | C6: Client. Name | D6: Client. Name | E6: =SQRT(0^2 + 0^2 + 0^2 + 0^2) | F6: =SQRT(0^2 + 0^2 + 0^2 + 0^2)
B7: Client .Address | C7: Client .Address | D7: Client .Address | E7: =SQRT(0^2 + 0^2 + 0^2 + 0^2) | F7: =SQRT(0^2 + 0^2 + 0^2 + 0^2)
B8: Reservation | C8: Reservation | D8: Reservation | E8: =0 | F8: =0
B9: Reservation .Pickup_Day | C9: Reservation .Pickup_Day | D9: Reservation .pickupDate | E9: =SQRT(0^2 + 0^2 + 0^2 + 0^2) | F9: =SQRT(0^2 + 0^2 + 1^2 + 0^2)
B10: Reservation .Return_Day | C10: Reservation .Return_Day | D10: \ | E10: =SQRT(0^2 + 0^2 + 0^2 + 0^2) | F10: =SQRT(1^2 + 1^2 + 1^2 + 1^2)
B11: \ | C11: \ | D11: Reservation .reservationID | E11: =SQRT(0^2 + 0^2 + 0^2 + 0^2) | F11: =SQRT(1^2 + 1^2 + 1^2 + 1^2)
B12: \ | C12: \ | D12: Reservation .clientNIN | E12: =SQRT(0^2 + 0^2 + 0^2 + 0^2) | F12: =SQRT(1^2 + 1^2 + 1^2 + 1^2)
B13: \ | C13: \ | D13: Reservation .modelName | E13: =SQRT(0^2 + 0^2 + 0^2 + 0^2) | F13: =SQRT(1^2 + 1^2 + 1^2 + 1^2)
B14: \ | C14: \ | D14: Reservation .StoreName | E14: =SQRT(0^2 + 0^2 + 0^2 + 0^2) | F14: =SQRT(1^2 + 1^2 + 1^2 + 1^2)
B15: Bicycle | C15: Bicycle | D15: Bicycle | E15: =0 | F15: =0
B16: Bicycle .Number | C16: Bicycle .ID | D16: Bicycle .bicycleID | E16: =SQRT(0^2 + 0^2 + 1^2 + 0^2) | F16: =SQRT(0^2 + 0^2 + 1^2 + 0^2)
B17: \ | C17: \ | D17: Bicycle .modelName | E17: =SQRT(0^2 + 0^2 + 0^2 + 0^2) | F17: =SQRT(1^2 + 1^2 + 1^2 + 1^2)
B18: BicycleModel | C18: BicycleModel | D18: BicycleModel | E18: =0 | F18: =0
B19: BicycleModel .Name | C19: BicycleModel .Name | D19: Bicycle .modelName | E19: =SQRT(0^2 + 0^2 + 0^2 + 0^2) | F19: =SQRT(0^2 + 0^2 + 1^2 + 0^2)
B20: BicycleModel .Type | C20: \ | D20: BicycleModel .Type | E20: =SQRT(1^2 + 1^2 + 1^2 + 1^2) | F20: =SQRT(0^2 + 0^2 + 0^2 + 0^2)
B21: BicycleModel .No_Gears | C21: BicycleModel .No_Gears | D21: BicycleModel .NumberofGears | E21: =SQRT(0^2 + 0^2 + 0^2 + 0^2) | F21: =SQRT(0^2 + 0^2 + 0^2 + 0^2)
B22: Store | C22: Store | D22: Store | E22: =0 | F22: =0
B23: Store .Name | C23: Store .Name | D23: Store .storeName | E23: =SQRT(0^2 + 0^2 + 0^2 + 0^2) | F23: =SQRT(0^2 + 0^2 + 0^2 + 0^2)
B24: Store .Address | C24: Store .Address | D24: Store .Address | E24: =SQRT(0^2 + 0^2 + 0^2 + 0^2) | F24: =SQRT(0^2 + 0^2 + 0^2 + 0^2)
B25: \ | C25: Type | D25: \ | E25: =SQRT(1^2 + 1^2 + 1^2 + 1^2) | F25: =SQRT(0^2 + 0^2 + 0^2 + 0^2)
B26: \ | C26: Road | D26: \ | E26: =SQRT(1^2 + 1^2 + 1^2 + 1^2) | F26: =SQRT(0^2 + 0^2 + 0^2 + 0^2)
B27: \ | C27: Mountain | D27: \ | E27: =SQRT(1^2 + 1^2 + 1^2 + 1^2) | F27: =SQRT(0^2 + 0^2 + 0^2 + 0^2)
B28: \ | C28: BMX | D28: \ | E28: =SQRT(1^2 + 1^2 + 1^2 + 1^2) | F28: =SQRT(0^2 + 0^2 + 0^2 + 0^2)
B29: \ | C29: Hybrid | D29: \ | E29: =SQRT(1^2 + 1^2 + 1^2 + 1^2) | F29: =SQRT(0^2 + 0^2 + 0^2 + 0^2)
B30: \ | C30: \ | D30: Rental | E30: =SQRT(0^2 + 0^2 + 0^2 + 0^2) | F30: =SQRT(1^2 + 1^2 + 1^2 + 1^2)
B31: \ | C31: \ | D31: Rental .rentalID | E31: =SQRT(0^2 + 0^2 + 0^2 + 0^2) | F31: =SQRT(1^2 + 1^2 + 1^2 + 1^2)
B32: \ | C32: \ | D32: Rental .bicycleID | E32: =SQRT(0^2 + 0^2 + 0^2 + 0^2) | F32: =SQRT(1^2 + 1^2 + 1^2 + 1^2)
B33: \ | C33: \ | D33: Rental .pickupDate | E33: =SQRT(0^2 + 0^2 + 0^2 + 0^2) | F33: =SQRT(1^2 + 1^2 + 1^2 + 1^2)
B34: \ | C34: \ | D34: Rental .returnDate | E34: =SQRT(0^2 + 0^2 + 0^2 + 0^2) | F34: =SQRT(1^2 + 1^2 + 1^2 + 1^2)
B35: Association (Client - Reservation) | C35: Association (Client - Reservation) | D35: Association (Client - Reservation) | E35: =SQRT(0^2 + 0^2 + 0^2 + 0^2) | F35: =SQRT(0^2 + 0^2 + 0^2 + 0^2)
B36: Association (Reservation - Bicycle) | C36: Association (Reservation - Bicycle) | D36: \ | E36: =SQRT(0^2 + 0^2 + 0^2 + 0^2) | F36: =SQRT(1^2 + 1^2 + 1^2 + 1^2)
B37: Association (Reservation - BicycleModel) | C37: Association (Reservation - BicycleModel) | D37: Association (Reservation - BicycleModel) | E37: =SQRT(0^2 + 0^2 + 0^2 + 0^2) | F37: =SQRT(0^2 + 0^2 + 0^2 + 0^2)
B38: Association (Bicycle - BycicleModel) | C38: Association (Bicycle - BycicleModel) | D38: Association (Bicycle - BycicleModel) | E38: =SQRT(0^2 + 0^2 + 0^2 + 0^2) | F38: =SQRT(0^2 + 0^2 + 0^2 + 1^2)
B39: Association (Reservation - Store) | C39: Association (Reservation - Store) | D39: Association (Reservation - Store) | E39: =SQRT(0^2 + 0^2 + 0^2 + 0^2) | F39: =SQRT(0^2 + 0^2 + 0^2 + 1^2)
B40: \ | C40: Association (Bycicle - Store) | D40: \ | E40: =SQRT(1^2 + 1^2 + 1^2 + 1^2) | F40: =SQRT(0^2 + 0^2 + 0^2 + 0^2)
B41: \ | C41: Association (BycicleModel - Type) | D41: \ | E41: =SQRT(1^2 + 1^2 + 1^2 + 1^2) | F41: =SQRT(0^2 + 0^2 + 0^2 + 0^2)
B42: \ | C42: Generalization (Type - Road) | D42: \ | E42: =SQRT(1^2 + 1^2 + 1^2 + 1^2) | F42: =SQRT(0^2 + 0^2 + 0^2 + 0^2)
B43: \ | C43: Generalization (Type - Mountain) | D43: \ | E43: =SQRT(1^2 + 1^2 + 1^2 + 1^2) | F43: =SQRT(0^2 + 0^2 + 0^2 + 0^2)
B44: \ | C44: Generalization (Type - BMX) | D44: \ | E44: =SQRT(1^2 + 1^2 + 1^2 + 1^2) | F44: =SQRT(0^2 + 0^2 + 0^2 + 0^2)
B45: \ | C45: Generalization (Type - Hybrid) | D45: \ | E45: =SQRT(1^2 + 1^2 + 1^2 + 1^2) | F45: =SQRT(0^2 + 0^2 + 0^2 + 0^2)
B46: \ | C46: \ | D46: Association (Bicycle - Rental) | E46: =SQRT(0^2 + 0^2 + 0^2 + 0^2) | F46: =SQRT(1^2 + 1^2 + 1^2 + 1^2)
D49: Total Distance | E49: =SQRT(SUMSQ(E3:E46)) | F49: =SQRT(SUMSQ(F3:F46))

Sheet Part 2 - 15
B2: Given Solution | C2: Human | D2: LLM | E2: Distance Human | F2: Distance LLM
B3: Staff Card | C3: Identity Card | D3: EmployeeCard | E3: =0.5 | F3: =0.5
B4: Staff Card .set last access() | C4: Identity Card .Issue() | D4: \ | E4: =SQRT(0^2 + 0^2 + 0^2 + 1^2 + 0^2 + 0^2) | F4: =SQRT(1^2 + 1^2 + 1^2 + 1^2 + 0.5^2 + 1^2)
B5: Access | C5: \ | D5: \ | E5: =1 | F5: =1
B6: Card | C6: Card | D6: \ | E6: =0 | F6: =1
B7: Guest Card | C7: Guest Card | D7: GuestCard | E7: =0 | F7: =0
B8: Card Reader | C8: Card Reader | D8: CardReader | E8: =0 | F8: =0
B9: Card Reader .insert staff card() | C9: Card Reader .insertcard() | D9: CardReader .VerifyCard() | E9: =SQRT(0^2 + 0^2 + 0^2 + 1^2 + 0^2 + 0^2) | F9: =SQRT(0^2 + 0^2 + 0^2 + 1^2 + 0^2 + 0^2)
B10: Card Reader .show success message() | C10: Card Reader .showsuccessmessage() | D10: \ | E10: =SQRT(0^2 + 0^2 + 0^2 + 0^2 + 0^2 + 0^2) | F10: =SQRT(1^2 + 1^2 + 1^2 + 1^2 + 0.5^2 + 1^2)
B11: Card Reader .show fail message() | C11: Card Reader .showfailmessage() | D11: \ | E11: =SQRT(0^2 + 0^2 + 0^2 + 0^2 + 0^2 + 0^2) | F11: =SQRT(1^2 + 1^2 + 1^2 + 1^2 + 0.5^2 + 1^2)
B12: Card Reader .eject card() | C12: Card Reader .ejectcard() | D12: \ | E12: =SQRT(0^2 + 0^2 + 0^2 + 0^2 + 0^2 + 0^2) | F12: =SQRT(1^2 + 1^2 + 1^2 + 1^2 + 0.5^2 + 1^2)
B13: Signal | C13: Sign | D13: \ | E13: =0 | F13: =1
B14: Car Park | C14: Car Park | D14: ParkingSpace | E14: =0 | F14: =0.5
B15: Barrier | C15: Barrier | D15: Barrier | E15: =0 | F15: =0
B16: Barrier .raise() | C16: Barrier .rise() | D16: Barrier .rise() | E16: =SQRT(0^2 + 0^2 + 0^2 + 0^2 + 0^2 + 0^2) | F16: =SQRT(0^2 + 0^2 + 0^2 + 0^2 + 0^2 + 0^2)
B17: \ | C17: Reception | D17: Reception | E17: =1 | F17: =1
B18: Generalization (Card - Staff Card) | C18: Generalization (Card - Identity Card) | D18: \ | E18: =SQRT(0^2 + 0^2 + 0^2 + 0^2) | F18: =SQRT(1^2 + 1^2 + 1^2 + 1^2)
B19: Generalization (Card - Access) | C19: \ | D19: \ | E19: =SQRT(1^2 + 1^2 + 1^2 + 1^2) | F19: =SQRT(1^2 + 1^2 + 1^2 + 1^2)
B20: Association (Guest card - Card) | C20: Generalization (Card - Guest Card) | D20: \ | E20: =SQRT(0^2 + 0^2 + 1^2 + 1^2) | F20: =SQRT(1^2 + 1^2 + 1^2 + 1^2)
B21: Aggregation (Card Reader - Guest Card) | C21: \ | D21: Association (Guest Card - CardReader) | E21: =SQRT(1^2 + 1^2 + 1^2 + 1^2) | F21: =SQRT(0^2 + 0^2 + 1^2 + 1^2)
B22: \ | C22: Association (Card - Card Reader) | D22: Association (Employee Card - CardReader) | E22: =SQRT(1^2 + 1^2 + 1^2 + 1^2) | F22: =SQRT(1^2 + 1^2 + 1^2 + 1^2)
B23: Aggregation (Card reader - Signal) | C23: \ | D23: \ | E23: =SQRT(1^2 + 1^2 + 1^2 + 1^2) | F23: =SQRT(1^2 + 1^2 + 1^2 + 1^2)
B24: Aggregation (Car Park - Card Reader) | C24: Composition (Car Park - Card Reader) | D24: \ | E24: =SQRT(0^2 + 0^2 + 1^2 + 1^2) | F24: =SQRT(1^2 + 1^2 + 1^2 + 1^2)
B25: Aggregation (Car Park - Barrier) | C25: Composition (Car Park - Barrier) | D25: Association (ParkingSpace - Barrier) | E25: =SQRT(0^2 + 0^2 + 1^2 + 1^2) | F25: =SQRT(0^2 + 0^2 + 1^2 + 1^2)
B26: Dependencies (Barrier - Signal) | C26: \ | D26: \ | E26: =SQRT(1^2 + 1^2 + 1^2 + 1^2) | F26: =SQRT(1^2 + 1^2 + 1^2 + 1^2)
B27: \ | C27: Composition (Car Park - Sign) | D27: \ | E27: =SQRT(1^2 + 1^2 + 1^2 + 1^2) | F27: =SQRT(1^2 + 1^2 + 1^2 + 1^2)
B28: \ | C28: Association (Card Reader - Barrier) | D28: Association (Card Reader - Barrier) | E28: =SQRT(1^2 + 1^2 + 1^2 + 1^2) | F28: =SQRT(1^2 + 1^2 + 1^2 + 1^2)
B29: \ | C29: Association (Guest Card - Reception) | D29: Association (Guest Card - Reception) | E29: =SQRT(1^2 + 1^2 + 1^2 + 1^2) | F29: =SQRT(1^2 + 1^2 + 1^2 + 1^2)
D32: Total Distance | E32: =SQRT(SUMSQ(E3:E29)) | F32: =SQRT(SUMSQ(F3:F29))

Sheet Part 2 - 17
B2: Given Solution | C2: Human | D2: LLM | E2: Distance Human | F2: Distance LLM
B3: Client | C3: Client | D3: Client | E3: =0 | F3: =0
B4: Contract | C4: Contract | D4: ContractComponent | E4: =0 | F4: =0.5
B5: Contract .getCharges() | C5: Contract .getCharges() | D5: ContractComponent .getCharges() | E5: =SQRT(0^2 + 0^2 + 0^2 + 0^2 + 0^2 + 0^2) | F5: =SQRT(0^2 + 0^2 + 0^2 + 0^2 + 0^2 + 0^2)
B6: Contract .getBalance() | C6: Contract .getBalance() | D6: ContractComponent .getBalance() | E6: =SQRT(0^2 + 0^2 + 0^2 + 0^2 + 0^2 + 0^2) | F6: =SQRT(0^2 + 0^2 + 0^2 + 0^2 + 0^2 + 0^2)
B7: Contract .setBalance() | C7: Contract .setBalance() | D7: ContractComponent .setBalance() | E7: =SQRT(0^2 + 0^2 + 0^2 + 0^2 + 0^2 + 0^2) | F7: =SQRT(0^2 + 0^2 + 0^2 + 0^2 + 0^2 + 0^2)
B8: Option | C8: Option | D8: ContractDecorator | E8: =0 | F8: =0.5
B9: Basic Contract | C9: Basic Contract | D9: BasicContract | E9: =0 | F9: =0
B10: Basic Contract .Balance | C10: Basic Contract .Balance | D10: Basic Contract .Balance | E10: =SQRT(0^2 + 0^2 + 0^2 + 0^2) | F10: =SQRT(0^2 + 0^2 + 0^2 + 0^2)
B11: Basic Contract .contractNumber | C11: Basic Contract .Number | D11: Basic Contract .contractNumber | E11: =SQRT(0^2 + 0^2 + 0^2 + 0^2) | F11: =SQRT(0^2 + 0^2 + 0^2 + 0^2)
B12: Data | C12: Data | D12: DataOption | E12: =0 | F12: =0
B13: SMS | C13: SMS | D13: SMSOption | E13: =0 | F13: =0
B14: Phone | C14: Phone | D14: MinutesOption | E14: =0 | F14: =0.5
B15: Double Transfer | C15: Double Transfer | D15: DOubleTransferRateOption | E15: =0 | F15: =0.5
B16: Generalization (Option - Data) | C16: Generalization (Option - Data) | D16: Generalization (Option - DataOption) | E16: =SQRT(0^2 + 0^2 + 0^2 + 0^2) | F16: =SQRT(0^2 + 0^2 + 0^2 + 0^2)
B17: Generalization (Option - SMS) | C17: Generalization (Option - SMS) | D17: Generalization (Option - SMSOption) | E17: =SQRT(0^2 + 0^2 + 0^2 + 0^2) | F17: =SQRT(0^2 + 0^2 + 0^2 + 0^2)
B18: Generalization (Option - Phone) | C18: Generalization (Option - Phone) | D18: Generalization (Option - MinutesOption) | E18: =SQRT(0^2 + 0^2 + 0^2 + 0^2) | F18: =SQRT(0^2 + 0^2 + 0^2 + 0^2)
B19: Generalization (Option - Double Transfer) | C19: Generalization (Option - Double Transfer) | D19: Generalization (Option - DoubleTransferRateOption) | E19: =SQRT(0^2 + 0^2 + 0^2 + 0^2) | F19: =SQRT(0^2 + 0^2 + 0^2 + 0^2)
B20: Implementation (Contract - Basic Contract) | C20: Association (Contract - Basic Contract) | D20: Implementation (ContractComponent - Basic Contract) | E20: =SQRT(0^2 + 0^2 + 1^2 + 1^2) | F20: =SQRT(0^2 + 0^2 + 0^2 + 0^2)
B21: Implementation (Contract - Option) | C21: \ | D21: Implementation (ContractComponent - ContractDecorator) | E21: =SQRT(1^2 + 1^2 + 1^2 + 1^2) | F21: =SQRT(0^2 + 0^2 + 0^2 + 0^2)
B22: Association (Contract - Option) | C22: Association (Contract - Option) | D22: \ | E22: =SQRT(0^2 + 0^2 + 0^2 + 0^2) | F22: =SQRT(1^2 + 1^2 + 1^2 + 1^2)
B23: Association (Contract - Client) | C23: Association (Contract - Client) | D23: Association (ContractComponent - Client) | E23: =SQRT(0^2 + 0^2 + 0^2 + 0^2) | F23: =SQRT(0^2 + 0^2 + 0^2 + 0^2)
D26: Total Distance | E26: =SQRT(SUMSQ(E3:E23)) | F26: =SQRT(SUMSQ(F3:F23))

Sheet Part 2 - 16
B2: Given Solution | C2: Human | D2: LLM | E2: Distance Human | F2: Distance LLM
B3: Person | C3: \ | D3: \ | E3: =1 | F3: =1
B4: Person .Name | C4: Client\Employee .Name | D4: Client\Employee .Name | E4: =SQRT(0^2 + 0^2 + 0^2 + 0^2) | F4: =SQRT(0^2 + 0^2 + 0^2 + 0^2)
B5: Employee | C5: Employee | D5: Employee | E5: =0 | F5: =0
B6: Customer | C6: Client | D6: Client | E6: =0.5 | F6: =0.5
B7: OrganizationalUnit | C7: Division | D7: Division | E7: =0.5 | F7: =0.5
B8: Branch | C8: Branch | D8: Branch | E8: =0 | F8: =0
B9: Branch .Address | C9: Branch .Address | D9: Branch .Address | E9: =SQRT(0^2 + 0^2 + 0^2 + 0^2) | F9: =SQRT(0^2 + 0^2 + 0^2 + 0^2)
B10: Branch .Number | C10: Branch .Number | D10: Branch .Number | E10: =SQRT(0^2 + 0^2 + 0^2 + 0^2) | F10: =SQRT(0^2 + 0^2 + 0^2 + 0^2)
B11: Account | C11: Account | D11: Account | E11: =0 | F11: =0
B12: Account .number | C12: Account .number | D12: Account .number | E12: =SQRT(0^2 + 0^2 + 0^2 + 0^2) | F12: =SQRT(0^2 + 0^2 + 0^2 + 0^2)
B13: Account .balance | C13: Account .balance | D13: Account .balance | E13: =SQRT(0^2 + 0^2 + 0^2 + 0^2) | F13: =SQRT(0^2 + 0^2 + 0^2 + 0^2)
B14: Account .creditoroverdraftLimit | C14: Account .creditLimit | D14: Account .creditLimit | E14: =SQRT(0^2 + 0^2 + 0^2 + 0^2) | F14: =SQRT(0^2 + 0^2 + 0^2 + 0^2)
B15: AccountType | C15: AccountType | D15: \ | E15: =0 | F15: =1
B16: AccountType .InterestRate | C16: AccountType .InterestRate | D16: \ | E16: =SQRT(0^2 + 0^2 + 0^2 + 0^2) | F16: =SQRT(1^2 + 1^2 + 1^2 + 1^2)
B17: AccountType .MonthlyFee | C17: AccountType .MonthlyFee | D17: \ | E17: =SQRT(0^2 + 0^2 + 0^2 + 0^2) | F17: =SQRT(1^2 + 1^2 + 1^2 + 1^2)
B18: AccountType .checksAllowed | C18: AccountType .checksAllowed | D18: \ | E18: =SQRT(0^2 + 0^2 + 0^2 + 0^2) | F18: =SQRT(1^2 + 1^2 + 1^2 + 1^2)
B19: AccountType .insuranceAvailable | C19: AccountType .insuranceAvailable | D19: \ | E19: =SQRT(0^2 + 0^2 + 0^2 + 0^2) | F19: =SQRT(1^2 + 1^2 + 1^2 + 1^2)
B20: ChequingAccount | C20: ChequingAccount | D20: CheckingAccount | E20: =0 | F20: =0
B21: MortgageAccount | C21: MortgageAccount | D21: MortgageAccount | E21: =0 | F21: =0
B22: MortgageAccount .collateral Property | C22: MortgageAccount .collateral Property | D22: MortgageAccunt .Property Collateral | E22: =SQRT(0^2 + 0^2 + 0^2 + 0^2) | F22: =SQRT(0^2 + 0^2 + 0^2 + 0^2)
B23: CreditCardAccount | C23: CreditCardAccount | D23: CreditCardAccount | E23: =0 | F23: =0
B24: CreditCardAccount .expiryDate | C24: CreditCardAccount .expiryDate | D24: CreditCardAccount .expiryDate | E24: =SQRT(0^2 + 0^2 + 0^2 + 0^2) | F24: =SQRT(0^2 + 0^2 + 0^2 + 0^2)
B25: CreditCard | C25: CreditCard | D25: \ | E25: =0 | F25: =1
B26: CreditCard .name | C26: CreditCard .name | D26: \ | E26: =SQRT(0^2 + 0^2 + 0^2 + 0^2) | F26: =SQRT(1^2 + 1^2 + 1^2 + 1^2)
B27: Subdivision | C27: Subdivision | D27: \ | E27: =0 | F27: =1
B28: \ | C28: Manager | D28: \ | E28: =1 | F28: =0
B29: \ | C29: Joint Account | D29: Joint Account | E29: =1 | F29: =1
B30: \ | C30: \ | D30: PersonalBanker | E30: =SQRT(0^2 + 0^2 + 0^2 + 0^2) | F30: =1
B31: \ | C31: \ | D31: OObank | E31: =SQRT(0^2 + 0^2 + 0^2 + 0^2) | F31: =1
B32: Generalization (Person - Employee) | C32: \ | D32: \ | E32: =SQRT(1^2 + 1^2 + 1^2 + 1^2) | F32: =SQRT(1^2 + 1^2 + 1^2 + 1^2)
B33: Generalization (Person - Customer) | C33: \ | D33: \ | E33: =SQRT(1^2 + 1^2 + 1^2 + 1^2) | F33: =SQRT(1^2 + 1^2 + 1^2 + 1^2)
B34: Association (Employee - Customer) | C34: Association (Employee - Client) | D34: \ | E34: =SQRT(0^2 + 0^2 + 0^2 + 0^2) | F34: =SQRT(1^2 + 1^2 + 1^2 + 1^2)
B35: Association (OrganizationalUnit - Employee) | C35: Composition (Division - Employee) | D35: \ | E35: =SQRT(0^2 + 0^2 + 1^2 + 1^2) | F35: =SQRT(1^2 + 1^2 + 1^2 + 1^2)
B36: Association (Employee - OrganizationalUnit) | C36: \ | D36: \ | E36: =SQRT(1^2 + 1^2 + 1^2 + 1^2) | F36: =SQRT(1^2 + 1^2 + 1^2 + 1^2)
B37: Generalization (OrganizationalUnit - Branch) | C37: \ | D37: Association (Division - Branch) | E37: =SQRT(1^2 + 1^2 + 1^2 + 1^2) | F37: =SQRT(0^2 + 0^2 + 1^2 + 1^2)
B38: Association (Branch - Account) | C38: \ | D38: Association (Branch - Account) | E38: =SQRT(1^2 + 1^2 + 1^2 + 1^2) | F38: =SQRT(0^2 + 0^2 + 0^2 + 0^2)
B39: Association (AccountType - Account) | C39: Association (AccountType - Account) | D39: \ | E39: =SQRT(0^2 + 0^2 + 0^2 + 0^2) | F39: =SQRT(1^2 + 1^2 + 1^2 + 1^2)
B40: Association (Customer - Account) | C40: Composition (Client - Account) | D40: \ | E40: =SQRT(0^2 + 0^2 + 1^2 + 1^2) | F40: =SQRT(1^2 + 1^2 + 1^2 + 1^2)
B41: Generalization (Account - ChequingAccount) | C41: Generalization (Account - ChequingAccount) | D41: Generalization (Account - ChequingAccount) | E41: =SQRT(0^2 + 0^2 + 0^2 + 0^2) | F41: =SQRT(0^2 + 0^2 + 0^2 + 0^2)
B42: Generalization (Account - MortgageAccount) | C42: Generalization (Account - MortgageAccount) | D42: Generalization (Account - MortgageAccount) | E42: =SQRT(0^2 + 0^2 + 0^2 + 0^2) | F42: =SQRT(0^2 + 0^2 + 0^2 + 0^2)
B43: Generalization (Account - CreditCardAccount) | C43: Generalization (Account - CreditCardAccount) | D43: Generalization (Account - CreditCardAccount) | E43: =SQRT(0^2 + 0^2 + 0^2 + 0^2) | F43: =SQRT(0^2 + 0^2 + 0^2 + 0^2)
B44: Association (CreditCard - CreditCardAccount) | C44: Association (CreditCard - CreditCardAccount) | D44: \ | E44: =SQRT(0^2 + 0^2 + 0^2 + 0^2) | F44: =SQRT(1^2 + 1^2 + 1^2 + 1^2)
B45: Composition (OrganizationalUnit - Subdivision) | C45: Composition (Division - Subdivision) | D45: \ | E45: =SQRT(0^2 + 0^2 + 1^2 + 0^2) | F45: =SQRT(1^2 + 1^2 + 1^2 + 1^2)
B46: \ | C46: Aggregation (Division - Manager) | D46: \ | E46: =SQRT(1^2 + 1^2 + 1^2 + 1^2) | F46: =SQRT(0^2 + 0^2 + 0^2 + 0^2)
B47: \ | C47: Generalization (Employee - Manager) | D47: \ | E47: =SQRT(1^2 + 1^2 + 1^2 + 1^2) | F47: =SQRT(0^2 + 0^2 + 0^2 + 0^2)
B48: \ | C48: Generalization (Subdivision - Branch) | D48: \ | E48: =SQRT(1^2 + 1^2 + 1^2 + 1^2) | F48: =SQRT(0^2 + 0^2 + 0^2 + 0^2)
B49: \ | C49: Association (Client - Branch) | D49: \ | E49: =SQRT(1^2 + 1^2 + 1^2 + 1^2) | F49: =SQRT(0^2 + 0^2 + 0^2 + 0^2)
B50: \ | C50: Composition (Joint Account - Client) | D50: \ | E50: =SQRT(1^2 + 1^2 + 1^2 + 1^2) | F50: =SQRT(0^2 + 0^2 + 0^2 + 0^2)
B51: \ | C51: Generalization (Account - JointAccount) | D51: Generalization (Account - JointAccount) | E51: =SQRT(1^2 + 1^2 + 1^2 + 1^2) | F51: =SQRT(1^2 + 1^2 + 1^2 + 1^2)
B52: \ | C52: \ | D52: Association (OOBank - Branch) | E52: =SQRT(0^2 + 0^2 + 0^2 + 0^2) | F52: =SQRT(1^2 + 1^2 + 1^2 + 1^2)
B53: \ | C53: \ | D53: Association (OOBank - Division) | E53: =SQRT(0^2 + 0^2 + 0^2 + 0^2) | F53: =SQRT(1^2 + 1^2 + 1^2 + 1^2)
B54: \ | C54: \ | D54: Generalization (Employee - PersonalBanker) | E54: =SQRT(0^2 + 0^2 + 0^2 + 0^2) | F54: =SQRT(1^2 + 1^2 + 1^2 + 1^2)
B55: \ | C55: \ | D55: Association (Client - PersonalBanker) | E55: =SQRT(0^2 + 0^2 + 0^2 + 0^2) | F55: =SQRT(1^2 + 1^2 + 1^2 + 1^2)
D58: Total Distance | E58: =SQRT(SUMSQ(E3:E55)) | F58: =SQRT(SUMSQ(F3:F55))

Sheet Part 2 - 18
B2: Given Solution | C2: Human | D2: LLM | E2: Distance Human | F2: Distance LLM
B3: User | C3: User | D3: User | E3: =0 | F3: =0
B4: User .last_name | C4: User .lastname | D4: User .fullname | E4: =SQRT(0^2 + 0^2 + 0^2 + 0^2) | F4: =SQRT(0^2 + 0^2 + 1^2 + 0^2)
B5: User .first_name | C5: User .firstname | D5: \ | E5: =SQRT(0^2 + 0^2 + 0^2 + 0^2) | F5: =SQRT(1^2 + 1^2 + 1^2 + 1^2)
B6: User .borrow_history | C6: \ | D6: \ | E6: =SQRT(1^2 + 1^2 + 1^2 + 1^2) | F6: =SQRT(1^2 + 1^2 + 1^2 + 1^2)
B7: \ | C7: User .borrow() | D7: User .borrowBook() | E7: =SQRT(1^2 + 1^2 + 1^2 + 1^2 + 0.5^2 + 1^2) | F7: =SQRT(1^2 + 1^2 + 1^2 + 1^2 + 0.5^2 + 1^2)
B8: Under_aged | C8: UnderAged | D8: UnderagedUser | E8: =0 | F8: =0
B9: Under_aged .id_student | C9: UnderAged .studentcard | D9: UnderagedUser .studentCard | E9: =SQRT(0^2 + 0^2 + 0^2 + 0^2) | F9: =SQRT(0^2 + 0^2 + 0^2 + 1^2)
B10: Adult | C10: Adult | D10: AdultUser | E10: =0 | F10: =0
B11: Adult .id | C11: Adult .idcard | D11: AdultUser .idCard | E11: =SQRT(0^2 + 0^2 + 0^2 + 0^2) | F11: =SQRT(0^2 + 0^2 + 0^2 + 1^2)
B12: Borrow | C12: History | D12: BorrowRecord | E12: =0.5 | F12: =0
B13: Borrow .Date | C13: History .date | D13: BorrowRecord .borrowDate | E13: =SQRT(0^2 + 0^2 + 0^2 + 1^2) | F13: =SQRT(0^2 + 0^2 + 0^2 + 0^2)
B14: Borrow .book | C14: History . Books | D14: BorrowRecord .book | E14: =SQRT(0^2 + 0^2 + 0^2 + 1^2) | F14: =SQRT(0^2 + 0^2 + 0^2 + 0^2)
B15: Book | C15: Book | D15: Book | E15: 0 | F15: =0
B16: Book .author | C16: Book .author | D16: Book .author | E16: =SQRT(0^2 + 0^2 + 0^2 + 0^2) | F16: =SQRT(0^2 + 0^2 + 0^2 + 0^2)
B17: Book .title | C17: Book .title | D17: Book .title | E17: =SQRT(0^2 + 0^2 + 0^2 + 0^2) | F17: =SQRT(0^2 + 0^2 + 0^2 + 0^2)
B18: Library | C18: Library | D18: Library | E18: =0 | F18: =0
B19: Library .Books | C19: Library .Books | D19: Library .books | E19: =SQRT(0^2 + 0^2 + 0^2 + 0^2) | F19: =SQRT(0^2 + 0^2 + 0^2 + 0^2)
B20: Generalization (User - Under_aged) | C20: Generalization (User - UnderAged) | D20: Generalization (User - UnderAgedUser) | E20: =SQRT(0^2 + 0^2 + 0^2 + 0^2) | F20: =SQRT(0^2 + 0^2 + 0^2 + 0^2)
B21: Generalization (User - Adult) | C21: Generalizarion (User - Adult) | D21: Generalizarion (User - AdultUser) | E21: =SQRT(0^2 + 0^2 + 0^2 + 0^2) | F21: =SQRT(0^2 + 0^2 + 0^2 + 0^2)
B22: Aggregation (User - Borrow) | C22: Composition (User - History) | D22: Composition (User - BorrowRecord) | E22: =SQRT(0^2 + 0^2 + 1^2 + 0^2) | F22: =SQRT(0^2 + 0^2 + 1^2 + 0^2)
B23: Association (User - Book) | C23: Association (User - Book) | D23: \ | E23: =SQRT(0^2 + 0^2 + 0^2 + 1^2) | F23: =SQRT(1^2 + 1^2 + 1^2 + 1^2)
B24: Aggregation (Library - Book) | C24: Aggregation (Library - Book) | D24: Aggregation (Library - Book) | E24: =SQRT(0^2 + 0^2 + 0^2 + 0^2) | F24: =SQRT(0^2 + 0^2 + 0^2 + 0^2)
B25: Dependencies (Book - Borrow) | C25: Aggregation (Book - History) | D25: \ | E25: =SQRT(0^2 + 0^2 + 1^2 + 0^2) | F25: =SQRT(1^2 + 1^2 + 1^2 + 1^2)
D28: Total Distance | E28: =SQRT(SUMSQ(E3:E25)) | F28: =SQRT(SUMSQ(F3:F25))

Sheet Part 2 - 19
B2: Given Solution | C2: Human | D2: LLM | E2: Distance Human | F2: Distance LLM
B3: User | C3: User | D3: \ | E3: =0 | F3: =1
B4: User .id | C4: User .id | D4: \ | E4: =SQRT(0^2 + 0^2 + 0^2 + 0^2) | F4: =SQRT(1^2 + 1^2 + 1^2 + 1^2)
B5: User .FirstName | C5: User .FirstName | D5: Doctor\Patient .name | E5: =SQRT(0^2 + 0^2 + 0^2 + 0^2) | F5: =SQRT(0^2 + 0^2 + 0^2 + 0^2)
B6: User .LastName | C6: User .LastName | D6: \ | E6: =SQRT(0^2 + 0^2 + 0^2 + 0^2) | F6: =SQRT(1^2 + 1^2 + 1^2 + 1^2)
B7: User .Login() | C7: User .Login() | D7: \ | E7: =SQRT(0^2 + 0^2 + 0^2 + 0^2 + 0^2 + 0^2) | F7: =SQRT(1^2 + 1^2 + 1^2 + 1^2 + 0.5^2 + 1^2)
B8: User .Logout() | C8: User .Logout() | D8: \ | E8: =SQRT(0^2 + 0^2 + 0^2 + 0^2 + 0^2 + 0^2) | F8: =SQRT(1^2 + 1^2 + 1^2 + 1^2 + 0.5^2 + 1^2)
B9: Doctor | C9: Doctor | D9: Doctor | E9: =0 | F9: =0
B10: Doctor .graduationYear | C10: \ | D10: \ | E10: =SQRT(1^2 + 1^2 + 1^2 + 1^2) | F10: =SQRT(1^2 + 1^2 + 1^2 + 1^2)
B11: Doctor .FieldOfActivity | C11: Doctor .Field | D11: \ | E11: =SQRT(0^2 + 0^2 + 1^2 + 0^2) | F11: =SQRT(1^2 + 1^2 + 1^2 + 1^2)
B12: Doctor .CreateSchedule() | C12: Doctor .CreateSchedule() | D12: \ | E12: =SQRT(0^2 + 0^2 + 0^2 + 0^2 + 0^2 + 0^2) | F12: =SQRT(1^2 + 1^2 + 1^2 + 1^2 + 0.5^2 + 1^2)
B13: Doctor .CheckOfficeAvailability() | C13: Doctor .CheckOfficeAvailability() | D13: \ | E13: =SQRT(0^2 + 0^2 + 0^2 + 0^2 + 0^2 + 0^2) | F13: =SQRT(1^2 + 1^2 + 1^2 + 1^2 + 0.5^2 + 1^2)
B14: Patient | C14: Patient | D14: Patient | E14: =0 | F14: =0
B15: Patienti .Age | C15: Patienti .Age | D15: \ | E15: =SQRT(0^2 + 0^2 + 0^2 + 0^2) | F15: =SQRT(1^2 + 1^2 + 1^2 + 1^2)
B16: Patienti .Address | C16: Patienti .Address | D16: \ | E16: =SQRT(0^2 + 0^2 + 0^2 + 0^2) | F16: =SQRT(1^2 + 1^2 + 1^2 + 1^2)
B17: Patient .CreateAppointment() | C17: Patient .CreateAppointment() | D17: \ | E17: =SQRT(0^2 + 0^2 + 0^2 + 0^2 + 0^2 + 0^2) | F17: =SQRT(1^2 + 1^2 + 1^2 + 1^2 + 0.5^2 + 1^2)
B18: Schedule | C18: Schedule | D18: Schedule | E18: =0 | F18: =0
B19: Schedule .id | C19: Schedule .id | D19: \ | E19: =SQRT(0^2 + 0^2 + 0^2 + 0^2) | F19: =SQRT(1^2 + 1^2 + 1^2 + 1^2)
B20: Schedule .StartDate | C20: Schedule .StartDate | D20: Schedule .StartTime | E20: =SQRT(0^2 + 0^2 + 0^2 + 0^2) | F20: =SQRT(0^2 + 0^2 + 1^2 + 1^2)
B21: Schedule .EndDate | C21: Schedule .EndDate | D21: Schedule .EndTime | E21: =SQRT(0^2 + 0^2 + 0^2 + 0^2) | F21: =SQRT(0^2 + 0^2 + 1^2 + 1^2)
B22: Office | C22: Office | D22: Office | E22: =0 | F22: =0
B23: Office .id | C23: Office .id | D23: Office .OfficeNumber | E23: =SQRT(0^2 + 0^2 + 0^2 + 0^2) | F23: =SQRT(0^2 + 0^2 + 1^2 + 0^2)
B24: Office .Name | C24: Office .Name | D24: \ | E24: =SQRT(0^2 + 0^2 + 0^2 + 0^2) | F24: =SQRT(1^2 + 1^2 + 1^2 + 1^2)
B25: Appointment | C25: Appointment | D25: Appointment | E25: =0 | F25: =0
B26: Appointment .id | C26: Appointment .id | D26: \ | E26: =SQRT(0^2 + 0^2 + 0^2 + 0^2) | F26: =SQRT(1^2 + 1^2 + 1^2 + 1^2)
B27: Appointment .StartDate | C27: Appointment .StartDate | D27: Appointment .StartTime | E27: =SQRT(0^2 + 0^2 + 0^2 + 0^2) | F27: =SQRT(0^2 + 0^2 + 1^2 + 1^2)
B28: Appointment .EndDate | C28: Appointment .EndDate | D28: Appointment .EndTime | E28: =SQRT(0^2 + 0^2 + 0^2 + 0^2) | F28: =SQRT(0^2 + 0^2 + 1^2 + 1^2)
B29: BloodTest | C29: BloodTest | D29: \ | E29: =0 | F29: =1
B30: Consultation | C30: Consultation | D30: \ | E30: =0 | F30: =1
B31: Surgery | C31: Surgery | D31: \ | E31: =0 | F31: =1
B32: \ | C32: \ | D32: AppointmentType | E32: =0 | F32: =1
B33: Generalization (User - Doctor) | C33: Generalization (User - Doctor) | D33: \ | E33: =SQRT(0^2 + 0^2 + 0^2 + 0^2) | F33: =SQRT(1^2 + 1^2 + 1^2 + 1^2)
B34: Generalization (User - Patient) | C34: Generalization (User - Patient) | D34: \ | E34: =SQRT(0^2 + 0^2 + 0^2 + 0^2) | F34: =SQRT(1^2 + 1^2 + 1^2 + 1^2)
B35: Aggregation (Schedule - Doctor) | C35: Aggregation (Schedule - Doctor) | D35: Association (Schedule - Doctor) | E35: =SQRT(0^2 + 0^2 + 0^2 + 0^2) | F35: =SQRT(0^2 + 0^2 + 1^2 + 0^2)
B36: Aggregation (Office - Schedule) | C36: Aggregation (Office - Schedule) | D36: Association (Office - Schedule) | E36: =SQRT(0^2 + 0^2 + 0^2 + 0^2) | F36: =SQRT(0^2 + 0^2 + 1^2 + 0^2)
B37: Aggregation (Appointment - Patient) | C37: Aggregation (Appointment - Patient) | D37: Association (Appointment - Patient) | E37: =SQRT(0^2 + 0^2 + 0^2 + 0^2) | F37: =SQRT(0^2 + 0^2 + 1^2 + 0^2)
B38: Composition (Schedule - Appointment) | C38: Composition (Schedule - Appointment) | D38: \ | E38: =SQRT(0^2 + 0^2 + 0^2 + 0^2) | F38: =SQRT(1^2 + 1^2 + 1^2 + 1^2)
B39: Generalization (Appointment - BloodTest) | C39: Generalization (Appointment - BloodTest) | D39: \ | E39: =SQRT(0^2 + 0^2 + 0^2 + 0^2) | F39: =SQRT(1^2 + 1^2 + 1^2 + 1^2)
B40: Generalization (Appointment - Consultation) | C40: Generalization (Appointment - Consultation) | D40: \ | E40: =SQRT(0^2 + 0^2 + 0^2 + 0^2) | F40: =SQRT(1^2 + 1^2 + 1^2 + 1^2)
B41: Generalization (Appointment - Surgery) | C41: Generalization (Appointment - Surgery) | D41: \ | E41: =SQRT(0^2 + 0^2 + 0^2 + 0^2) | F41: =SQRT(1^2 + 1^2 + 1^2 + 1^2)
B42: \ | C42: Association (Doctor - Office) | D42: \ | E42: =SQRT(1^2 + 1^2 + 1^2 + 1^2) | F42: =SQRT(0^2 + 0^2 + 0^2 + 0^2)
B43: \ | C43: Association (Doctor - Patient) | D43: \ | E43: =SQRT(1^2 + 1^2 + 1^2 + 1^2) | F43: =SQRT(0^2 + 0^2 + 0^2 + 0^2)
B44: \ | C44: Association (Patient - Schedule) | D44: \ | E44: =SQRT(1^2 + 1^2 + 1^2 + 1^2) | F44: =SQRT(0^2 + 0^2 + 0^2 + 0^2)
B45: \ | C45: \ | D45: Association (Doctor - Appointment) | E45: =SQRT(0^2 + 0^2 + 0^2 + 0^2) | F45: =SQRT(1^2 + 1^2 + 1^2 + 1^2)
B46: \ | C46: \ | D46: Association (Office - Appointment) | E46: =SQRT(0^2 + 0^2 + 0^2 + 0^2) | F46: =SQRT(1^2 + 1^2 + 1^2 + 1^2)
D49: Total Distance | E49: =SQRT(SUMSQ(E3:E46)) | F49: =SQRT(SUMSQ(F3:F46))

Sheet Part 2 - 20
B2: Given Solution | C2: Human | D2: LLM | E2: Distance Human | F2: Distance LLM
B3: Web User | C3: Web User | D3: Web User | E3: =0 | F3: =0
B4: Web User .login_id | C4: Web User .loginname | D4: WebUser .username | E4: =SQRT(0^2 + 0^2 + 1^2 + 0^2) | F4: =SQRT(0^2 + 0^2 + 1^2 + 0^2)
B5: Web User .password | C5: \ | D5: \ | E5: =SQRT(1^2 + 1^2 + 1^2 + 1^2) | F5: =SQRT(1^2 + 1^2 + 1^2 + 1^2)
B6: Web User .state | C6: Web User .state | D6: Web User .state | E6: =SQRT(0^2 + 0^2 + 0^2 + 1^2) | F6: =SQRT(0^2 + 0^2 + 0^2 + 0^2)
B7: UserState | C7: UserState | D7: WebUserState | E7: =0 | F7: =0
B8: Shopping Cart | C8: Shopping Cart | D8: Shopping Cart | E8: =0 | F8: =0
B9: Shopping Cart .Created | C9: \ | D9: \ | E9: =SQRT(1^2 + 1^2 + 1^2 + 1^2) | F9: =SQRT(1^2 + 1^2 + 1^2 + 1^2)
B10: Customer | C10: Customer | D10: Customer | E10: =0 | F10: =0
B11: Customer .id | C11: Customer .id | D11: Customer .Customer.id | E11: =SQRT(0^2 + 0^2 + 0^2 + 0^2) | F11: =SQRT(0^2 + 0^2 + 0^2 + 0^2)
B12: Customer .address | C12: Customer .address | D12: \ | E12: =SQRT(0^2 + 0^2 + 0^2 + 1^2) | F12: =SQRT(1^2 + 1^2 + 1^2 + 1^2)
B13: Customer .phone | C13: Customer .phone | D13: \ | E13: =SQRT(0^2 + 0^2 + 0^2 + 1^2) | F13: =SQRT(1^2 + 1^2 + 1^2 + 1^2)
B14: Customer .email | C14: Customer .email | D14: \ | E14: =SQRT(0^2 + 0^2 + 0^2 + 0^2) | F14: =SQRT(1^2 + 1^2 + 1^2 + 1^2)
B15: Account | C15: Account | D15: Account | E15: =0 | F15: =0
B16: Account .id | C16: Account .id | D16: Account .id | E16: =SQRT(0^2 + 0^2 + 0^2 + 0^2) | F16: =SQRT(0^2 + 0^2 + 0^2 + 0^2)
B17: Account .billing_address | C17: \ | D17: \ | E17: =SQRT(1^2 + 1^2 + 1^2 + 1^2) | F17: =SQRT(1^2 + 1^2 + 1^2 + 1^2)
B18: Account .is_closed | C18: \ | D18: \ | E18: =SQRT(1^2 + 1^2 + 1^2 + 1^2) | F18: =SQRT(1^2 + 1^2 + 1^2 + 1^2)
B19: Account .open | C19: \ | D19: \ | E19: =SQRT(1^2 + 1^2 + 1^2 + 1^2) | F19: =SQRT(1^2 + 1^2 + 1^2 + 1^2)
B20: Account .closed | C20: \ | D20: \ | E20: =SQRT(1^2 + 1^2 + 1^2 + 1^2) | F20: =SQRT(1^2 + 1^2 + 1^2 + 1^2)
B21: Payment | C21: Payment | D21: Payment | E21: =0 | F21: =0
B22: Payment .id | C22: Payment .id | D22: Payment .id | E22: =SQRT(0^2 + 0^2 + 0^2 + 0^2) | F22: =SQRT(0^2 + 0^2 + 0^2 + 0^2)
B23: Payment .paid | C23: \ | D23: \ | E23: =SQRT(1^2 + 1^2 + 1^2 + 1^2) | F23: =SQRT(1^2 + 1^2 + 1^2 + 1^2)
B24: Payment .total | C24: Payment .Amount | D24: \ | E24: =SQRT(0^2 + 0^2 + 1^2 + 0^2) | F24: =SQRT(1^2 + 1^2 + 1^2 + 1^2)
B25: Payment .details | C25: \ | D25: \ | E25: =SQRT(1^2 + 1^2 + 1^2 + 1^2) | F25: =SQRT(1^2 + 1^2 + 1^2 + 1^2)
B26: Order | C26: Order | D26: Order | E26: =0 | F26: =0
B27: Order .number | C27: Order .id | D27: Order .OrderId | E27: =SQRT(0^2 + 0^2 + 1^2 + 0^2) | F27: =SQRT(0^2 + 0^2 + 1^2 + 0^2)
B28: Order .ordered | C28: \ | D28: \ | E28: =SQRT(1^2 + 1^2 + 1^2 + 1^2) | F28: =SQRT(1^2 + 1^2 + 1^2 + 1^2)
B29: Order .shipped | C29: \ | D29: \ | E29: =SQRT(1^2 + 1^2 + 1^2 + 1^2) | F29: =SQRT(1^2 + 1^2 + 1^2 + 1^2)
B30: Order .ship_to | C30: \ | D30: \ | E30: =SQRT(1^2 + 1^2 + 1^2 + 1^2) | F30: =SQRT(1^2 + 1^2 + 1^2 + 1^2)
B31: Order .status | C31: Order .status | D31: Order .OrderStatus | E31: =SQRT(0^2 + 0^2 + 1^2 + 0^2) | F31: =SQRT(0^2 + 0^2 + 0^2 + 0^2)
B32: Order .total | C32: \ | D32: \ | E32: =SQRT(1^2 + 1^2 + 1^2 + 1^2) | F32: =SQRT(1^2 + 1^2 + 1^2 + 1^2)
B33: LineItem | C33: LineItem | D33: LineItem | E33: =0 | F33: =0
B34: LineItem .quantity | C34: LineItem .quantity | D34: LineItem .quantity | E34: =SQRT(0^2 + 0^2 + 0^2 + 0^2) | F34: =SQRT(0^2 + 0^2 + 0^2 + 0^2)
B35: LineItem .Price | C35: LineItem .Price | D35: \ | E35: =SQRT(0^2 + 0^2 + 0^2 + 0^2) | F35: =SQRT(1^2 + 1^2 + 1^2 + 1^2)
B36: Product | C36: Product | D36: Product | E36: =0 | F36: =0
B37: Product .id | C37: Product .id | D37: Product .ProductId | E37: =SQRT(0^2 + 0^2 + 0^2 + 0^2) | F37: 0
B38: Product .name | C38: Product .name | D38: \ | E38: =SQRT(0^2 + 0^2 + 0^2 + 0^2) | F38: =SQRT(1^2 + 1^2 + 1^2 + 1^2)
B39: Product .supplier | C39: \ | D39: \ | E39: =SQRT(1^2 + 1^2 + 1^2 + 1^2) | F39: =SQRT(1^2 + 1^2 + 1^2 + 1^2)
B40: OrderStatus | C40: OrderStatus | D40: OrderStatus | E40: =0 | F40: =0
B41: Association (Web User - Customer) | C41: Association (Web User - Customer) | D41: Generalization (Web User - Customer) | E41: =SQRT(0^2 + 0^2 + 0^2 + 0^2) | F41: =SQRT(0^2 + 0^2 + 1^2 + 1^2)
B42: Association (Web User - Shopping Cart) | C42: Association (Web User - Shopping Cart) | D42: \ | E42: =SQRT(0^2 + 0^2 + 0^2 + 0^2) | F42: =SQRT(1^2 + 1^2 + 1^2 + 1^2)
B43: Composition (Customer - Account) | C43: Composition (Customer - Account) | D43: Association (Customer - Account) | E43: =SQRT(0^2 + 0^2 + 0^2 + 0^2) | F43: =SQRT(0^2 + 0^2 + 1^2 + 0^2)
B44: Composition (Account - Shopping Cart) | C44: Composition (Account - Shopping Cart) | D44: Association (Account - ShoppingCart) | E44: =SQRT(0^2 + 0^2 + 0^2 + 0^2) | F44: =SQRT(0^2 + 0^2 + 1^2 + 0^2)
B45: Composition (Account - Order) | C45: Composition (Account - Order) | D45: Association (Account - Order) | E45: =SQRT(0^2 + 0^2 + 0^2 + 0^2) | F45: =SQRT(0^2 + 0^2 + 1^2 + 0^2)
B46: Association (Account - Payment) | C46: Association (Account - Payment) | D46: Association (Account - Payment) | E46: =SQRT(0^2 + 0^2 + 0^2 + 0^2) | F46: =SQRT(0^2 + 0^2 + 0^2 + 0^2)
B47: \ | C47: \ | D47: Association (Payment - Account) | E47: =SQRT(0^2 + 0^2 + 0^2 + 0^2) | F47: =SQRT(1^2 + 1^2 + 1^2 + 1^2)
B48: Association (Payment - Order) | C48: Association (Payment - Order) | D48: \ | E48: =SQRT(0^2 + 0^2 + 0^2 + 0^2) | F48: =SQRT(1^2 + 1^2 + 1^2 + 1^2)
B49: Association (Shopping Cart - LineItem) | C49: Association (Shopping Cart - LineItem) | D49: Association (Shopping Cart - LineItem) | E49: =SQRT(0^2 + 0^2 + 0^2 + 0^2) | F49: =SQRT(0^2 + 0^2 + 0^2 + 1^2)
B50: Association (LineItem - Product) | C50: Association (LineItem - Product) | D50: Association (LineItem - Product) | E50: =SQRT(0^2 + 0^2 + 0^2 + 0^2) | F50: =SQRT(0^2 + 0^2 + 0^2 + 1^2)
B51: Association (Order - LineItem) | C51: Association (Order - LineItem) | D51: Association (Order - LineItem) | E51: =SQRT(0^2 + 0^2 + 0^2 + 0^2) | F51: =SQRT(0^2 + 0^2 + 0^2 + 1^2)
B52: \ | C52: Dependecy (WebUser - UserState) | D52: \ | E52: =SQRT(1^2 + 1^2 + 1^2 + 1^2) | F52: =SQRT(0^2 + 0^2 + 0^2 + 0^2)
B53: \ | C53: Dependency (Order - OrderStatus) | D53: \ | E53: =SQRT(1^2 + 1^2 + 1^2 + 1^2) | F53: =SQRT(0^2 + 0^2 + 0^2 + 0^2)
D56: Total Distance | E56: =SQRT(SUMSQ(E3:E53)) | F56: =SQRT(SUMSQ(F3:F53))

Sheet Part 2 - Tot
C2: Human | D2: LLM | E2: Difference
B3: 1 | C3: ='Part 2 - 1'!E42 | D3: ='Part 2 - 1'!F42 | E3: =D3-C3
B4: 2 | C4: ='Part 2 - 2'!E31 | D4: ='Part 2 - 2'!F31 | E4: =D4-C4
B5: 3 | C5: ='Part 2 - 3'!E60 | D5: ='Part 2 - 3'!F60 | E5: =D5-C5
B6: 4 | C6: ='Part 2 - 4'!E60 | D6: ='Part 2 - 4'!F60 | E6: =D6-C6
B7: 5 | C7: ='Part 2 - 5'!E48 | D7: ='Part 2 - 5'!F48 | E7: =D7-C7
B8: 6 | C8: ='Part 2 - 6'!E43 | D8: ='Part 2 - 6'!F43 | E8: =D8-C8
B9: 7 | C9: ='Part 2 - 7'!E24 | D9: ='Part 2 - 7'!F24 | E9: =D9-C9
B10: 8 | C10: ='Part 2 - 8'!E32 | D10: ='Part 2 - 8'!F32 | E10: =D10-C10
B11: 9 | C11: ='Part 2 - 9'!E43 | D11: ='Part 2 - 9'!F43 | E11: =D11-C11
B12: 10 | C12: ='Part 2 - 10'!E34 | D12: ='Part 2 - 10'!F34 | E12: =D12-C12
B13: 11 | C13: ='Part 2 - 11'!E31 | D13: ='Part 2 - 11'!F31 | E13: =D13-C13
B14: 12 | C14: ='Part 2 - 12'!E30 | D14: ='Part 2 - 12'!F30 | E14: =D14-C14
B15: 13 | C15: ='Part 2 - 13'!E42 | D15: ='Part 2 - 13'!F42 | E15: =D15-C15
B16: 14 | C16: ='Part 2 - 14'!E49 | D16: ='Part 2 - 14'!F49 | E16: =D16-C16
B17: 15 | C17: ='Part 2 - 15'!E32 | D17: ='Part 2 - 15'!F32 | E17: =D17-C17
B18: 16 | C18: ='Part 2 - 16'!E58 | D18: ='Part 2 - 16'!F58 | E18: =D18-C18
B19: 17 | C19: ='Part 2 - 17'!E26 | D19: ='Part 2 - 17'!F26 | E19: =D19-C19
B20: 18 | C20: ='Part 2 - 18'!E28 | D20: ='Part 2 - 18'!F28 | E20: =D20-C20
B21: 19 | C21: ='Part 2 - 19'!E49 | D21: ='Part 2 - 19'!F49 | E21: =D21-C21
B22: 20 | C22: ='Part 2 - 20'!E56 | D22: ='Part 2 - 20'!F56 | E22: =D22-C22
B25: AVG distance | C25: =AVERAGE(C3:C22) | D25: =AVERAGE(D3:D22) | E25: =AVERAGE(E3:E22)

Sheet Estimated Difficulty
B2: Exercise | C2: Classes | D2: Attributes + Operations | E2: Associations | F2: ED 1 | G2: ED 2 | H2: ED 3 | I2: AVG ED | J2: ED = Estimated Difficulty. 1 = Easy 5=Hard
B3: 1 | C3: 6 | D3: =10+7 | E3: 7 | F3: 3 | G3: 2 | H3: 2 | I3: =AVERAGE(F3:H3)
B4: 2 | C4: 6 | D4: =12 + 23 | E4: 5 | F4: 2 | G4: 1 | H4: 1 | I4: =AVERAGE(F4:H4)
B5: 3 | C5: 7 | D5: 12 | E5: 8 | F5: 5 | G5: 5 | H5: 4 | I5: =AVERAGE(F5:H5)
B6: 4 | C6: 6 | D6: 31 | E6: 7 | F6: 4 | G6: 3 | H6: 3 | I6: =AVERAGE(F6:H6)
B7: 5 | C7: 8 | D7: =15+3 | E7: 11 | F7: 2 | G7: 2 | H7: 3 | I7: =AVERAGE(F7:H7)
B8: 6 | C8: 9 | D8: 12 | E8: 12 | F8: 4 | G8: 4 | H8: 3 | I8: =AVERAGE(F8:H8)
B9: 7 | C9: 6 | D9: 5 | E9: 7 | F9: 1 | G9: 1 | H9: 1 | I9: =AVERAGE(F9:H9)
B10: 8 | C10: 7 | D10: 11 | E10: 8 | F10: 2 | G10: 2 | H10: 2 | I10: =AVERAGE(F10:H10)
B11: 9 | C11: 9 | D11: 13 | E11: 10 | F11: 3 | G11: 3 | H11: 2 | I11: =AVERAGE(F11:H11)
B12: 10 | C12: 7 | D12: 15 | E12: 7 | F12: 2 | G12: 3 | H12: 3 | I12: =AVERAGE(F12:H12)
B13: 11 | C13: 6 | D13: 11 | E13: 9 | F13: 3 | G13: 4 | H13: 3 | I13: =AVERAGE(F13:H13)
B14: 12 | C14: 6 | D14: 11 | E14: 5 | F14: 2 | G14: 3 | H14: 2 | I14: =AVERAGE(F14:H14)
B15: 13 | C15: 8 | D15: 19 | E15: 8 | F15: 2 | G15: 1 | H15: 2 | I15: =AVERAGE(F15:H15)
B16: 14 | C16: 5 | D16: 12 | E16: 5 | F16: 3 | G16: 2 | H16: 3 | I16: =AVERAGE(F16:H16)
B17: 15 | C17: 8 | D17: =0+6 | E17: 8 | F17: 4 | G17: 5 | H17: 4 | I17: =AVERAGE(F17:H17)
B18: 16 | C18: 11 | D18: 13 | E18: 13 | F18: 4 | G18: 3 | H18: 2 | I18: =AVERAGE(F18:H18)
B19: 17 | C19: 8 | D19: =2+3 | E19: 8 | F19: 3 | G19: 2 | H19: 2 | I19: =AVERAGE(F19:H19)
B20: 18 | C20: 6 | D20: 10 | E20: 6 | F20: 2 | G20: 2 | H20: 1 | I20: =AVERAGE(F20:H20)
B21: 19 | C21: 9 | D21: =15+5 | E21: 9 | F21: 4 | G21: 4 | H21: 4 | I21: =AVERAGE(F21:H21)
B22: 20 | C22: 10 | D22: 28 | E22: 10 | F22: 5 | G22: 5 | H22: 4 | I22: =AVERAGE(F22:H22)
B24: Average | C24: =AVERAGE(C3:C22) | D24: =AVERAGE(D3:D22) | E24: =AVERAGE(E3:E22) | F24: =AVERAGE(F3:F22) | G24: =AVERAGE(G3:G22) | H24: =AVERAGE(H3:H22) | I24: =AVERAGE(I3:I22)
